{"note":"This file is an internal implementation detail to speed up HTML report generation. Its format can change at any time. You might be looking for the JSON report: https://coverage.rtfd.io/cmd.html#cmd-json","format":5,"version":"7.10.6","globals":"f4b2f38a7331f196b022f4436d22635c","files":{"z_58ef8218edfcd01a___init___py":{"hash":"220b98aeb89a34e4ed7c1b2310d6d283","index":{"url":"z_58ef8218edfcd01a___init___py.html","file":"opera_cloud_mcp/__init__.py","description":"","nums":{"precision":0,"n_files":1,"n_statements":5,"n_excluded":0,"n_missing":0,"n_branches":0,"n_partial_branches":0,"n_missing_branches":0}}},"z_58ef8218edfcd01a___main___py":{"hash":"7b973d4481d46b4a524ee4ee0d80d868","index":{"url":"z_58ef8218edfcd01a___main___py.html","file":"opera_cloud_mcp/__main__.py","description":"","nums":{"precision":0,"n_files":1,"n_statements":2,"n_excluded":2,"n_missing":2,"n_branches":0,"n_partial_branches":0,"n_missing_branches":0}}},"z_37279972ca6c983f___init___py":{"hash":"02c89ea0309e5ef333026e1968f49fe6","index":{"url":"z_37279972ca6c983f___init___py.html","file":"opera_cloud_mcp/auth/__init__.py","description":"","nums":{"precision":0,"n_files":1,"n_statements":73,"n_excluded":0,"n_missing":37,"n_branches":0,"n_partial_branches":0,"n_missing_branches":0}}},"z_37279972ca6c983f_audit_logger_py":{"hash":"8a5518428ea5de49d036a457757868d7","index":{"url":"z_37279972ca6c983f_audit_logger_py.html","file":"opera_cloud_mcp/auth/audit_logger.py","description":"","nums":{"precision":0,"n_files":1,"n_statements":303,"n_excluded":0,"n_missing":213,"n_branches":0,"n_partial_branches":0,"n_missing_branches":0}}},"z_37279972ca6c983f_audit_sqlmodel_py":{"hash":"59c57536d95a8c92363eaa383eecff7c","index":{"url":"z_37279972ca6c983f_audit_sqlmodel_py.html","file":"opera_cloud_mcp/auth/audit_sqlmodel.py","description":"","nums":{"precision":0,"n_files":1,"n_statements":63,"n_excluded":0,"n_missing":63,"n_branches":0,"n_partial_branches":0,"n_missing_branches":0}}},"z_37279972ca6c983f_oauth_handler_py":{"hash":"95ced26ecd07f2a5b09de8e15e81ccb2","index":{"url":"z_37279972ca6c983f_oauth_handler_py.html","file":"opera_cloud_mcp/auth/oauth_handler.py","description":"","nums":{"precision":0,"n_files":1,"n_statements":277,"n_excluded":0,"n_missing":62,"n_branches":0,"n_partial_branches":0,"n_missing_branches":0}}},"z_37279972ca6c983f_secure_oauth_handler_py":{"hash":"deb00a20fb73183483d94ea20ce24ac9","index":{"url":"z_37279972ca6c983f_secure_oauth_handler_py.html","file":"opera_cloud_mcp/auth/secure_oauth_handler.py","description":"","nums":{"precision":0,"n_files":1,"n_statements":296,"n_excluded":0,"n_missing":226,"n_branches":0,"n_partial_branches":0,"n_missing_branches":0}}},"z_37279972ca6c983f_security_enhancements_py":{"hash":"643053f8cbd301f4d4d3c141afc39901","index":{"url":"z_37279972ca6c983f_security_enhancements_py.html","file":"opera_cloud_mcp/auth/security_enhancements.py","description":"","nums":{"precision":0,"n_files":1,"n_statements":236,"n_excluded":0,"n_missing":152,"n_branches":0,"n_partial_branches":0,"n_missing_branches":0}}},"z_37279972ca6c983f_security_middleware_py":{"hash":"0f4354f6b6b9fdb703f0dcc855fe7434","index":{"url":"z_37279972ca6c983f_security_middleware_py.html","file":"opera_cloud_mcp/auth/security_middleware.py","description":"","nums":{"precision":0,"n_files":1,"n_statements":354,"n_excluded":0,"n_missing":293,"n_branches":0,"n_partial_branches":0,"n_missing_branches":0}}},"z_58ef8218edfcd01a_cli_py":{"hash":"61dbc24e1bd0944b3c1c1ed92ff5bd8b","index":{"url":"z_58ef8218edfcd01a_cli_py.html","file":"opera_cloud_mcp/cli.py","description":"","nums":{"precision":0,"n_files":1,"n_statements":106,"n_excluded":2,"n_missing":106,"n_branches":0,"n_partial_branches":0,"n_missing_branches":0}}},"z_692e39b0e5d2a0b5___init___py":{"hash":"41db25168a901b3126c003a77131b75c","index":{"url":"z_692e39b0e5d2a0b5___init___py.html","file":"opera_cloud_mcp/clients/__init__.py","description":"","nums":{"precision":0,"n_files":1,"n_statements":2,"n_excluded":0,"n_missing":0,"n_branches":0,"n_partial_branches":0,"n_missing_branches":0}}},"z_b6c5a45813e26057___init___py":{"hash":"7a700b6dd3cce6628e67856d017cc726","index":{"url":"z_b6c5a45813e26057___init___py.html","file":"opera_cloud_mcp/clients/api_clients/__init__.py","description":"","nums":{"precision":0,"n_files":1,"n_statements":0,"n_excluded":0,"n_missing":0,"n_branches":0,"n_partial_branches":0,"n_missing_branches":0}}},"z_b6c5a45813e26057_activities_py":{"hash":"b7b2e0106ed9e1132deccff1a8ef21ff","index":{"url":"z_b6c5a45813e26057_activities_py.html","file":"opera_cloud_mcp/clients/api_clients/activities.py","description":"","nums":{"precision":0,"n_files":1,"n_statements":284,"n_excluded":0,"n_missing":125,"n_branches":0,"n_partial_branches":0,"n_missing_branches":0}}},"z_b6c5a45813e26057_block_py":{"hash":"fa8b2bb14d48379fb8bdd8e3860af2a1","index":{"url":"z_b6c5a45813e26057_block_py.html","file":"opera_cloud_mcp/clients/api_clients/block.py","description":"","nums":{"precision":0,"n_files":1,"n_statements":186,"n_excluded":0,"n_missing":186,"n_branches":0,"n_partial_branches":0,"n_missing_branches":0}}},"z_b6c5a45813e26057_cashiering_py":{"hash":"6d9221adb4ae55dfc61d6426be125454","index":{"url":"z_b6c5a45813e26057_cashiering_py.html","file":"opera_cloud_mcp/clients/api_clients/cashiering.py","description":"","nums":{"precision":0,"n_files":1,"n_statements":208,"n_excluded":0,"n_missing":208,"n_branches":0,"n_partial_branches":0,"n_missing_branches":0}}},"z_b6c5a45813e26057_crm_py":{"hash":"fa4242d94ff063c3485bb1352ee68379","index":{"url":"z_b6c5a45813e26057_crm_py.html","file":"opera_cloud_mcp/clients/api_clients/crm.py","description":"","nums":{"precision":0,"n_files":1,"n_statements":225,"n_excluded":0,"n_missing":49,"n_branches":0,"n_partial_branches":0,"n_missing_branches":0}}},"z_b6c5a45813e26057_front_office_py":{"hash":"bdb00b7946eb5dd3b039bca7e79397e6","index":{"url":"z_b6c5a45813e26057_front_office_py.html","file":"opera_cloud_mcp/clients/api_clients/front_office.py","description":"","nums":{"precision":0,"n_files":1,"n_statements":163,"n_excluded":0,"n_missing":8,"n_branches":0,"n_partial_branches":0,"n_missing_branches":0}}},"z_b6c5a45813e26057_housekeeping_py":{"hash":"a0a1a0133ad4523bc53549e1bd825bfc","index":{"url":"z_b6c5a45813e26057_housekeeping_py.html","file":"opera_cloud_mcp/clients/api_clients/housekeeping.py","description":"","nums":{"precision":0,"n_files":1,"n_statements":188,"n_excluded":0,"n_missing":188,"n_branches":0,"n_partial_branches":0,"n_missing_branches":0}}},"z_b6c5a45813e26057_inventory_py":{"hash":"0a8934649aeed9d00b48a63ac2a01d44","index":{"url":"z_b6c5a45813e26057_inventory_py.html","file":"opera_cloud_mcp/clients/api_clients/inventory.py","description":"","nums":{"precision":0,"n_files":1,"n_statements":232,"n_excluded":0,"n_missing":232,"n_branches":0,"n_partial_branches":0,"n_missing_branches":0}}},"z_b6c5a45813e26057_rates_py":{"hash":"e048449aa4360cb217bcf4595fbb8ad0","index":{"url":"z_b6c5a45813e26057_rates_py.html","file":"opera_cloud_mcp/clients/api_clients/rates.py","description":"","nums":{"precision":0,"n_files":1,"n_statements":223,"n_excluded":0,"n_missing":223,"n_branches":0,"n_partial_branches":0,"n_missing_branches":0}}},"z_b6c5a45813e26057_reservations_py":{"hash":"c8d8eb21e8b3a02d0b1879ca1a2f675c","index":{"url":"z_b6c5a45813e26057_reservations_py.html","file":"opera_cloud_mcp/clients/api_clients/reservations.py","description":"","nums":{"precision":0,"n_files":1,"n_statements":280,"n_excluded":0,"n_missing":62,"n_branches":0,"n_partial_branches":0,"n_missing_branches":0}}},"z_692e39b0e5d2a0b5_base_client_py":{"hash":"ebd07a3987fd3a681095edcb7148c9e2","index":{"url":"z_692e39b0e5d2a0b5_base_client_py.html","file":"opera_cloud_mcp/clients/base_client.py","description":"","nums":{"precision":0,"n_files":1,"n_statements":577,"n_excluded":0,"n_missing":231,"n_branches":0,"n_partial_branches":0,"n_missing_branches":0}}},"z_692e39b0e5d2a0b5_base_client_refactored_py":{"hash":"142f163d10453fa338c9d9132a69e7d3","index":{"url":"z_692e39b0e5d2a0b5_base_client_refactored_py.html","file":"opera_cloud_mcp/clients/base_client_refactored.py","description":"","nums":{"precision":0,"n_files":1,"n_statements":508,"n_excluded":0,"n_missing":508,"n_branches":0,"n_partial_branches":0,"n_missing_branches":0}}},"z_692e39b0e5d2a0b5_client_factory_py":{"hash":"f14b8ba925bad1ac9e5785ed9d2c5755","index":{"url":"z_692e39b0e5d2a0b5_client_factory_py.html","file":"opera_cloud_mcp/clients/client_factory.py","description":"","nums":{"precision":0,"n_files":1,"n_statements":101,"n_excluded":0,"n_missing":61,"n_branches":0,"n_partial_branches":0,"n_missing_branches":0}}},"z_a15f9f4d1acec077___init___py":{"hash":"6fba15b70534579f17f1590ee3100e1e","index":{"url":"z_a15f9f4d1acec077___init___py.html","file":"opera_cloud_mcp/config/__init__.py","description":"","nums":{"precision":0,"n_files":1,"n_statements":2,"n_excluded":0,"n_missing":0,"n_branches":0,"n_partial_branches":0,"n_missing_branches":0}}},"z_a15f9f4d1acec077_security_settings_py":{"hash":"49d3ca6bc4b3c6c9887f2d06c483d9ef","index":{"url":"z_a15f9f4d1acec077_security_settings_py.html","file":"opera_cloud_mcp/config/security_settings.py","description":"","nums":{"precision":0,"n_files":1,"n_statements":173,"n_excluded":0,"n_missing":93,"n_branches":0,"n_partial_branches":0,"n_missing_branches":0}}},"z_a15f9f4d1acec077_settings_py":{"hash":"dfe7594e6f4c7b50ad317d679d528e27","index":{"url":"z_a15f9f4d1acec077_settings_py.html","file":"opera_cloud_mcp/config/settings.py","description":"","nums":{"precision":0,"n_files":1,"n_statements":53,"n_excluded":0,"n_missing":20,"n_branches":0,"n_partial_branches":0,"n_missing_branches":0}}},"z_58ef8218edfcd01a_main_py":{"hash":"e99073bfd619ade4d74be1b7fd5bfb7c","index":{"url":"z_58ef8218edfcd01a_main_py.html","file":"opera_cloud_mcp/main.py","description":"","nums":{"precision":0,"n_files":1,"n_statements":139,"n_excluded":2,"n_missing":111,"n_branches":0,"n_partial_branches":0,"n_missing_branches":0}}},"z_37fddd2ff037de4f___init___py":{"hash":"c8050f0547a8f76f0e22ea5545e2c04b","index":{"url":"z_37fddd2ff037de4f___init___py.html","file":"opera_cloud_mcp/models/__init__.py","description":"","nums":{"precision":0,"n_files":1,"n_statements":0,"n_excluded":0,"n_missing":0,"n_branches":0,"n_partial_branches":0,"n_missing_branches":0}}},"z_37fddd2ff037de4f_common_py":{"hash":"c3518002ed8a3154e50b29b5270d6095","index":{"url":"z_37fddd2ff037de4f_common_py.html","file":"opera_cloud_mcp/models/common.py","description":"","nums":{"precision":0,"n_files":1,"n_statements":47,"n_excluded":0,"n_missing":0,"n_branches":0,"n_partial_branches":0,"n_missing_branches":0}}},"z_37fddd2ff037de4f_financial_py":{"hash":"773939cee3084a3681f67b4a4d94670a","index":{"url":"z_37fddd2ff037de4f_financial_py.html","file":"opera_cloud_mcp/models/financial.py","description":"","nums":{"precision":0,"n_files":1,"n_statements":27,"n_excluded":0,"n_missing":0,"n_branches":0,"n_partial_branches":0,"n_missing_branches":0}}},"z_37fddd2ff037de4f_guest_py":{"hash":"c48b4ec441d44d8a089ba8f2fdac3560","index":{"url":"z_37fddd2ff037de4f_guest_py.html","file":"opera_cloud_mcp/models/guest.py","description":"","nums":{"precision":0,"n_files":1,"n_statements":260,"n_excluded":0,"n_missing":19,"n_branches":0,"n_partial_branches":0,"n_missing_branches":0}}},"z_37fddd2ff037de4f_reservation_py":{"hash":"75b89d52dc853f75d6d5826f014a5b3f","index":{"url":"z_37fddd2ff037de4f_reservation_py.html","file":"opera_cloud_mcp/models/reservation.py","description":"","nums":{"precision":0,"n_files":1,"n_statements":214,"n_excluded":0,"n_missing":0,"n_branches":0,"n_partial_branches":0,"n_missing_branches":0}}},"z_37fddd2ff037de4f_room_py":{"hash":"88b17815da84af8175938998bf509860","index":{"url":"z_37fddd2ff037de4f_room_py.html","file":"opera_cloud_mcp/models/room.py","description":"","nums":{"precision":0,"n_files":1,"n_statements":27,"n_excluded":0,"n_missing":0,"n_branches":0,"n_partial_branches":0,"n_missing_branches":0}}},"z_bc5530ecc82d25cf___init___py":{"hash":"c644842e0a32145de618872235aa4e0b","index":{"url":"z_bc5530ecc82d25cf___init___py.html","file":"opera_cloud_mcp/resources/__init__.py","description":"","nums":{"precision":0,"n_files":1,"n_statements":2,"n_excluded":0,"n_missing":0,"n_branches":0,"n_partial_branches":0,"n_missing_branches":0}}},"z_bc5530ecc82d25cf_api_specs_py":{"hash":"21f2e221e3c8b0630d69c792024d4ce4","index":{"url":"z_bc5530ecc82d25cf_api_specs_py.html","file":"opera_cloud_mcp/resources/api_specs.py","description":"","nums":{"precision":0,"n_files":1,"n_statements":36,"n_excluded":0,"n_missing":1,"n_branches":0,"n_partial_branches":0,"n_missing_branches":0}}},"z_bc5530ecc82d25cf_health_check_py":{"hash":"982fba29097b4ef6699047cc606b2549","index":{"url":"z_bc5530ecc82d25cf_health_check_py.html","file":"opera_cloud_mcp/resources/health_check.py","description":"","nums":{"precision":0,"n_files":1,"n_statements":66,"n_excluded":0,"n_missing":50,"n_branches":0,"n_partial_branches":0,"n_missing_branches":0}}},"z_58ef8218edfcd01a_server_py":{"hash":"74ee697a57d01b67c2245cb4bdc1653d","index":{"url":"z_58ef8218edfcd01a_server_py.html","file":"opera_cloud_mcp/server.py","description":"","nums":{"precision":0,"n_files":1,"n_statements":15,"n_excluded":2,"n_missing":15,"n_branches":0,"n_partial_branches":0,"n_missing_branches":0}}},"z_6ae3826fa9550496___init___py":{"hash":"fe8150e479b4e8b493cd0e3bf2f3bb28","index":{"url":"z_6ae3826fa9550496___init___py.html","file":"opera_cloud_mcp/tools/__init__.py","description":"","nums":{"precision":0,"n_files":1,"n_statements":0,"n_excluded":0,"n_missing":0,"n_branches":0,"n_partial_branches":0,"n_missing_branches":0}}},"z_6ae3826fa9550496_financial_tools_py":{"hash":"c2adc44a66ea4fb241f6d98099de14be","index":{"url":"z_6ae3826fa9550496_financial_tools_py.html","file":"opera_cloud_mcp/tools/financial_tools.py","description":"","nums":{"precision":0,"n_files":1,"n_statements":189,"n_excluded":0,"n_missing":124,"n_branches":0,"n_partial_branches":0,"n_missing_branches":0}}},"z_6ae3826fa9550496_guest_tools_py":{"hash":"bd3c3a6d460aa023b2ae23e517980ada","index":{"url":"z_6ae3826fa9550496_guest_tools_py.html","file":"opera_cloud_mcp/tools/guest_tools.py","description":"","nums":{"precision":0,"n_files":1,"n_statements":192,"n_excluded":0,"n_missing":134,"n_branches":0,"n_partial_branches":0,"n_missing_branches":0}}},"z_6ae3826fa9550496_operation_tools_py":{"hash":"52f143ca129bbd98f02f629fad1f40cf","index":{"url":"z_6ae3826fa9550496_operation_tools_py.html","file":"opera_cloud_mcp/tools/operation_tools.py","description":"","nums":{"precision":0,"n_files":1,"n_statements":204,"n_excluded":0,"n_missing":132,"n_branches":0,"n_partial_branches":0,"n_missing_branches":0}}},"z_6ae3826fa9550496_reservation_tools_py":{"hash":"5c46db45acbca2b1e1717e627fbb6bdb","index":{"url":"z_6ae3826fa9550496_reservation_tools_py.html","file":"opera_cloud_mcp/tools/reservation_tools.py","description":"","nums":{"precision":0,"n_files":1,"n_statements":196,"n_excluded":0,"n_missing":85,"n_branches":0,"n_partial_branches":0,"n_missing_branches":0}}},"z_6ae3826fa9550496_room_tools_py":{"hash":"53bc1424726b28ad9265b9c684dbcbcd","index":{"url":"z_6ae3826fa9550496_room_tools_py.html","file":"opera_cloud_mcp/tools/room_tools.py","description":"","nums":{"precision":0,"n_files":1,"n_statements":218,"n_excluded":0,"n_missing":157,"n_branches":0,"n_partial_branches":0,"n_missing_branches":0}}},"z_6ae3826fa9550496_tool_registry_py":{"hash":"89ba8fb86d134b5ebc2d468ec04194a6","index":{"url":"z_6ae3826fa9550496_tool_registry_py.html","file":"opera_cloud_mcp/tools/tool_registry.py","description":"","nums":{"precision":0,"n_files":1,"n_statements":209,"n_excluded":0,"n_missing":209,"n_branches":0,"n_partial_branches":0,"n_missing_branches":0}}},"z_4883c40a61b180de___init___py":{"hash":"1ab51c1f3209452bb1a8b25ec43cbf29","index":{"url":"z_4883c40a61b180de___init___py.html","file":"opera_cloud_mcp/utils/__init__.py","description":"","nums":{"precision":0,"n_files":1,"n_statements":2,"n_excluded":0,"n_missing":0,"n_branches":0,"n_partial_branches":0,"n_missing_branches":0}}},"z_4883c40a61b180de_cache_manager_py":{"hash":"df062cce4e3ff3072a9b6d4498c8dba7","index":{"url":"z_4883c40a61b180de_cache_manager_py.html","file":"opera_cloud_mcp/utils/cache_manager.py","description":"","nums":{"precision":0,"n_files":1,"n_statements":239,"n_excluded":0,"n_missing":156,"n_branches":0,"n_partial_branches":0,"n_missing_branches":0}}},"z_4883c40a61b180de_client_factory_py":{"hash":"1b5b208c5d1b297df0a08cb0bf67b44a","index":{"url":"z_4883c40a61b180de_client_factory_py.html","file":"opera_cloud_mcp/utils/client_factory.py","description":"","nums":{"precision":0,"n_files":1,"n_statements":63,"n_excluded":0,"n_missing":49,"n_branches":0,"n_partial_branches":0,"n_missing_branches":0}}},"z_4883c40a61b180de_connection_optimizer_py":{"hash":"bdb9e40a634a3d096b2c552b17ec5560","index":{"url":"z_4883c40a61b180de_connection_optimizer_py.html","file":"opera_cloud_mcp/utils/connection_optimizer.py","description":"","nums":{"precision":0,"n_files":1,"n_statements":149,"n_excluded":0,"n_missing":149,"n_branches":0,"n_partial_branches":0,"n_missing_branches":0}}},"z_4883c40a61b180de_exceptions_py":{"hash":"decfbd9b80573055e9f32d8a791b6111","index":{"url":"z_4883c40a61b180de_exceptions_py.html","file":"opera_cloud_mcp/utils/exceptions.py","description":"","nums":{"precision":0,"n_files":1,"n_statements":121,"n_excluded":0,"n_missing":61,"n_branches":0,"n_partial_branches":0,"n_missing_branches":0}}},"z_4883c40a61b180de_formatters_py":{"hash":"f1931ddc20eada3c5609a4ca7c737ad9","index":{"url":"z_4883c40a61b180de_formatters_py.html","file":"opera_cloud_mcp/utils/formatters.py","description":"","nums":{"precision":0,"n_files":1,"n_statements":62,"n_excluded":0,"n_missing":62,"n_branches":0,"n_partial_branches":0,"n_missing_branches":0}}},"z_4883c40a61b180de_observability_py":{"hash":"6189a73f8de507a55c1a537b85bca14b","index":{"url":"z_4883c40a61b180de_observability_py.html","file":"opera_cloud_mcp/utils/observability.py","description":"","nums":{"precision":0,"n_files":1,"n_statements":343,"n_excluded":0,"n_missing":237,"n_branches":0,"n_partial_branches":0,"n_missing_branches":0}}},"z_4883c40a61b180de_resilience_manager_py":{"hash":"dea2e3c991740a338ec7cea6f73ba4a1","index":{"url":"z_4883c40a61b180de_resilience_manager_py.html","file":"opera_cloud_mcp/utils/resilience_manager.py","description":"","nums":{"precision":0,"n_files":1,"n_statements":260,"n_excluded":0,"n_missing":260,"n_branches":0,"n_partial_branches":0,"n_missing_branches":0}}},"z_4883c40a61b180de_validators_py":{"hash":"f8964967f16d7e05f45924e14a985169","index":{"url":"z_4883c40a61b180de_validators_py.html","file":"opera_cloud_mcp/utils/validators.py","description":"","nums":{"precision":0,"n_files":1,"n_statements":86,"n_excluded":0,"n_missing":37,"n_branches":0,"n_partial_branches":0,"n_missing_branches":0}}}}}