[
    {
        "bin": "222718",
        "brand": "MASTERCARD",
        "type": "DEBIT",
        "category": "PLATINUM",
        "issuer": "NEPAL INVESTMENT BANK, LTD.",
        "phone": "",
        "website": "http://www.nibl.com.np",
        "country_code": "NP",
        "country_code_alpha3": "NPL",
        "country_name": "NEPAL"
    },
    {
        "bin": "222719",
        "brand": "MASTERCARD",
        "type": "DEBIT",
        "category": "STANDARD",
        "issuer": "NEPAL INVESTMENT MEGA BANK, LTD.",
        "phone": "",
        "website": "",
        "country_code": "NP",
        "country_code_alpha3": "NPL",
        "country_name": "NEPAL"
    },
    {
        "bin": "222846",
        "brand": "MASTERCARD",
        "type": "DEBIT",
        "category": "STANDARD",
        "issuer": "NEPAL INVESTMENT MEGA BANK, LTD.",
        "phone": "",
        "website": "",
        "country_code": "NP",
        "country_code_alpha3": "NPL",
        "country_name": "NEPAL"
    },
    {
        "bin": "222847",
        "brand": "MASTERCARD",
        "type": "DEBIT",
        "category": "STANDARD",
        "issuer": "NEPAL INVESTMENT MEGA BANK, LTD.",
        "phone": "",
        "website": "",
        "country_code": "NP",
        "country_code_alpha3": "NPL",
        "country_name": "NEPAL"
    },
    {
        "bin": "377175",
        "brand": "AMERICAN EXPRESS",
        "type": "CREDIT",
        "category": "PERSONAL",
        "issuer": "HIMALAYAN BANK, LTD.",
        "phone": "",
        "website": "http://www.himalayanbank.com",
        "country_code": "NP",
        "country_code_alpha3": "NPL",
        "country_name": "NEPAL"
    },
    {
        "bin": "377344",
        "brand": "AMERICAN EXPRESS",
        "type": "DEBIT",
        "category": "PREPAID RELOADABLE",
        "issuer": "HIMALAYAN BANK, LTD.",
        "phone": "",
        "website": "http://www.himalayanbank.com",
        "country_code": "NP",
        "country_code_alpha3": "NPL",
        "country_name": "NEPAL"
    },
    {
        "bin": "378254",
        "brand": "AMERICAN EXPRESS",
        "type": "DEBIT",
        "category": "PREPAID RELOADABLE",
        "issuer": "HIMALAYAN BANK, LTD.",
        "phone": "",
        "website": "http://www.himalayanbank.com",
        "country_code": "NP",
        "country_code_alpha3": "NPL",
        "country_name": "NEPAL"
    },
    {
        "bin": "401562",
        "brand": "VISA",
        "type": "CREDIT",
        "category": "CLASSIC",
        "issuer": "AGRICULTURAL DEVELOPMENT BANK, LTD.",
        "phone": "",
        "website": "",
        "country_code": "NP",
        "country_code_alpha3": "NPL",
        "country_name": "NEPAL"
    },
    {
        "bin": "401583",
        "brand": "VISA",
        "type": "CREDIT",
        "category": "CLASSIC",
        "issuer": "RASTRIYA BANIJYA BANK",
        "phone": "",
        "website": "",
        "country_code": "NP",
        "country_code_alpha3": "NPL",
        "country_name": "NEPAL"
    },
    {
        "bin": "402064",
        "brand": "VISA",
        "type": "CREDIT",
        "category": "CLASSIC",
        "issuer": "MACHHAPUCHCHHRE BANK, LTD.",
        "phone": "",
        "website": "",
        "country_code": "NP",
        "country_code_alpha3": "NPL",
        "country_name": "NEPAL"
    },
    {
        "bin": "402069",
        "brand": "VISA",
        "type": "DEBIT",
        "category": "CLASSIC",
        "issuer": "MACHHAPUCHCHHRE BANK, LTD.",
        "phone": "",
        "website": "",
        "country_code": "NP",
        "country_code_alpha3": "NPL",
        "country_name": "NEPAL"
    },
    {
        "bin": "402085",
        "brand": "VISA",
        "type": "DEBIT",
        "category": "PREPAID CLASSIC",
        "issuer": "MACHHAPUCHCHHRE BANK, LTD.",
        "phone": "",
        "website": "",
        "country_code": "NP",
        "country_code_alpha3": "NPL",
        "country_name": "NEPAL"
    },
    {
        "bin": "402153",
        "brand": "VISA",
        "type": "DEBIT",
        "category": "CLASSIC",
        "issuer": "",
        "phone": "",
        "website": "",
        "country_code": "NP",
        "country_code_alpha3": "NPL",
        "country_name": "NEPAL"
    },
    {
        "bin": "402487",
        "brand": "VISA",
        "type": "DEBIT",
        "category": "PREPAID",
        "issuer": "SUNRISE BANK, LTD.",
        "phone": "",
        "website": "",
        "country_code": "NP",
        "country_code_alpha3": "NPL",
        "country_name": "NEPAL"
    },
    {
        "bin": "402896",
        "brand": "VISA",
        "type": "DEBIT",
        "category": "CLASSIC",
        "issuer": "GLOBAL IME BANK, LTD.",
        "phone": "",
        "website": "",
        "country_code": "NP",
        "country_code_alpha3": "NPL",
        "country_name": "NEPAL"
    },
    {
        "bin": "402969",
        "brand": "VISA",
        "type": "DEBIT",
        "category": "CLASSIC",
        "issuer": "INDUSIND BANK, LTD.",
        "phone": "",
        "website": "http://www.indusind.com",
        "country_code": "NP",
        "country_code_alpha3": "NPL",
        "country_name": "NEPAL"
    },
    {
        "bin": "403019",
        "brand": "VISA",
        "type": "CREDIT",
        "category": "PLATINUM",
        "issuer": "NMB BANK, LTD.",
        "phone": "",
        "website": "http://www.nmbz.co.zw",
        "country_code": "NP",
        "country_code_alpha3": "NPL",
        "country_name": "NEPAL"
    },
    {
        "bin": "403110",
        "brand": "VISA",
        "type": "CREDIT",
        "category": "CLASSIC",
        "issuer": "SANIMA BANK, LTD.",
        "phone": "",
        "website": "",
        "country_code": "NP",
        "country_code_alpha3": "NPL",
        "country_name": "NEPAL"
    },
    {
        "bin": "403729",
        "brand": "VISA",
        "type": "CREDIT",
        "category": "CLASSIC",
        "issuer": "SANIMA BANK, LTD.",
        "phone": "",
        "website": "",
        "country_code": "NP",
        "country_code_alpha3": "NPL",
        "country_name": "NEPAL"
    },
    {
        "bin": "403735",
        "brand": "VISA",
        "type": "DEBIT",
        "category": "CLASSIC",
        "issuer": "SANIMA BANK, LTD.",
        "phone": "",
        "website": "",
        "country_code": "NP",
        "country_code_alpha3": "NPL",
        "country_name": "NEPAL"
    },
    {
        "bin": "404393",
        "brand": "VISA",
        "type": "DEBIT",
        "category": "CLASSIC",
        "issuer": "",
        "phone": "",
        "website": "",
        "country_code": "NP",
        "country_code_alpha3": "NPL",
        "country_name": "NEPAL"
    },
    {
        "bin": "404782",
        "brand": "VISA",
        "type": "CREDIT",
        "category": "GOLD",
        "issuer": "NEPAL INVESTMENT MEGA BANK, LTD.",
        "phone": "",
        "website": "",
        "country_code": "NP",
        "country_code_alpha3": "NPL",
        "country_name": "NEPAL"
    },
    {
        "bin": "405019",
        "brand": "VISA",
        "type": "CREDIT",
        "category": "CLASSIC",
        "issuer": "LAXMI SUNRISE BANK, LTD.",
        "phone": "",
        "website": "",
        "country_code": "NP",
        "country_code_alpha3": "NPL",
        "country_name": "NEPAL"
    },
    {
        "bin": "405229",
        "brand": "VISA",
        "type": "DEBIT",
        "category": "PREPAID",
        "issuer": "",
        "phone": "",
        "website": "",
        "country_code": "NP",
        "country_code_alpha3": "NPL",
        "country_name": "NEPAL"
    },
    {
        "bin": "405230",
        "brand": "VISA",
        "type": "DEBIT",
        "category": "CLASSIC",
        "issuer": "PRABHU BANK LTD.",
        "phone": "",
        "website": "",
        "country_code": "NP",
        "country_code_alpha3": "NPL",
        "country_name": "NEPAL"
    },
    {
        "bin": "405231",
        "brand": "VISA",
        "type": "CREDIT",
        "category": "GOLD",
        "issuer": "",
        "phone": "",
        "website": "",
        "country_code": "NP",
        "country_code_alpha3": "NPL",
        "country_name": "NEPAL"
    },
    {
        "bin": "405263",
        "brand": "VISA",
        "type": "CREDIT",
        "category": "CLASSIC",
        "issuer": "NEPAL INVESTMENT MEGA BANK, LTD.",
        "phone": "",
        "website": "",
        "country_code": "NP",
        "country_code_alpha3": "NPL",
        "country_name": "NEPAL"
    },
    {
        "bin": "405462",
        "brand": "VISA",
        "type": "DEBIT",
        "category": "CLASSIC",
        "issuer": "",
        "phone": "",
        "website": "",
        "country_code": "NP",
        "country_code_alpha3": "NPL",
        "country_name": "NEPAL"
    },
    {
        "bin": "405483",
        "brand": "VISA",
        "type": "CREDIT",
        "category": "CLASSIC",
        "issuer": "",
        "phone": "",
        "website": "",
        "country_code": "NP",
        "country_code_alpha3": "NPL",
        "country_name": "NEPAL"
    },
    {
        "bin": "405490",
        "brand": "VISA",
        "type": "DEBIT",
        "category": "CLASSIC",
        "issuer": "",
        "phone": "",
        "website": "",
        "country_code": "NP",
        "country_code_alpha3": "NPL",
        "country_name": "NEPAL"
    },
    {
        "bin": "405514",
        "brand": "VISA",
        "type": "DEBIT",
        "category": "CLASSIC",
        "issuer": "MUKTINATH BIKAS BANK, LTD.",
        "phone": "",
        "website": "",
        "country_code": "NP",
        "country_code_alpha3": "NPL",
        "country_name": "NEPAL"
    },
    {
        "bin": "405544",
        "brand": "VISA",
        "type": "DEBIT",
        "category": "PREPAID CLASSIC",
        "issuer": "LAXMI SUNRISE BANK, LTD.",
        "phone": "",
        "website": "",
        "country_code": "NP",
        "country_code_alpha3": "NPL",
        "country_name": "NEPAL"
    },
    {
        "bin": "405633",
        "brand": "VISA",
        "type": "CREDIT",
        "category": "GOLD",
        "issuer": "NEPAL INVESTMENT MEGA BANK, LTD.",
        "phone": "",
        "website": "",
        "country_code": "NP",
        "country_code_alpha3": "NPL",
        "country_name": "NEPAL"
    },
    {
        "bin": "405634",
        "brand": "VISA",
        "type": "DEBIT",
        "category": "CLASSIC",
        "issuer": "NEPAL INVESTMENT MEGA BANK, LTD.",
        "phone": "",
        "website": "",
        "country_code": "NP",
        "country_code_alpha3": "NPL",
        "country_name": "NEPAL"
    },
    {
        "bin": "405635",
        "brand": "VISA",
        "type": "DEBIT",
        "category": "ELECTRON",
        "issuer": "NEPAL INVESTMENT BANK, LTD.",
        "phone": "",
        "website": "http://www.nibl.com.np",
        "country_code": "NP",
        "country_code_alpha3": "NPL",
        "country_name": "NEPAL"
    },
    {
        "bin": "405636",
        "brand": "VISA",
        "type": "CREDIT",
        "category": "CLASSIC",
        "issuer": "NEPAL INVESTMENT MEGA BANK, LTD.",
        "phone": "",
        "website": "",
        "country_code": "NP",
        "country_code_alpha3": "NPL",
        "country_name": "NEPAL"
    },
    {
        "bin": "405673",
        "brand": "VISA",
        "type": "DEBIT",
        "category": "CLASSIC",
        "issuer": "NEPAL INVESTMENT BANK, LTD.",
        "phone": "",
        "website": "http://www.nibl.com.np",
        "country_code": "NP",
        "country_code_alpha3": "NPL",
        "country_name": "NEPAL"
    },
    {
        "bin": "405690",
        "brand": "VISA",
        "type": "DEBIT",
        "category": "CLASSIC",
        "issuer": "SHINE RESUNGA DEVELOPMENT BANK, LTD.",
        "phone": "",
        "website": "",
        "country_code": "NP",
        "country_code_alpha3": "NPL",
        "country_name": "NEPAL"
    },
    {
        "bin": "406142",
        "brand": "VISA",
        "type": "CREDIT",
        "category": "GOLD",
        "issuer": "STANDARD CHARTERED BANK",
        "phone": "+97771524029",
        "website": "https://www.sc.com",
        "country_code": "NP",
        "country_code_alpha3": "NPL",
        "country_name": "NEPAL"
    },
    {
        "bin": "406143",
        "brand": "VISA",
        "type": "DEBIT",
        "category": "PREPAID ELECTRON",
        "issuer": "STANDARD CHARTERED BANK",
        "phone": "+97771524029",
        "website": "https://www.sc.com",
        "country_code": "NP",
        "country_code_alpha3": "NPL",
        "country_name": "NEPAL"
    },
    {
        "bin": "406750",
        "brand": "VISA",
        "type": "DEBIT",
        "category": "ELECTRON",
        "issuer": "NABIL BANK LTD.",
        "phone": "",
        "website": "",
        "country_code": "NP",
        "country_code_alpha3": "NPL",
        "country_name": "NEPAL"
    },
    {
        "bin": "406866",
        "brand": "VISA",
        "type": "DEBIT",
        "category": "CLASSIC",
        "issuer": "KUMARI BANK, LTD.",
        "phone": "",
        "website": "http://www.kumaribank.com",
        "country_code": "NP",
        "country_code_alpha3": "NPL",
        "country_name": "NEPAL"
    },
    {
        "bin": "406886",
        "brand": "VISA",
        "type": "DEBIT",
        "category": "PREPAID CLASSIC",
        "issuer": "MAHALAXMI BIKAS BANK, LTD.",
        "phone": "",
        "website": "",
        "country_code": "NP",
        "country_code_alpha3": "NPL",
        "country_name": "NEPAL"
    },
    {
        "bin": "406888",
        "brand": "VISA",
        "type": "DEBIT",
        "category": "CLASSIC",
        "issuer": "KUMARI BANK, LTD.",
        "phone": "",
        "website": "http://www.kumaribank.com",
        "country_code": "NP",
        "country_code_alpha3": "NPL",
        "country_name": "NEPAL"
    },
    {
        "bin": "407038",
        "brand": "VISA",
        "type": "DEBIT",
        "category": "PREPAID CLASSIC",
        "issuer": "PRABHU BANK LTD.",
        "phone": "",
        "website": "",
        "country_code": "NP",
        "country_code_alpha3": "NPL",
        "country_name": "NEPAL"
    },
    {
        "bin": "407585",
        "brand": "VISA",
        "type": "CREDIT",
        "category": "CLASSIC",
        "issuer": "LAXMI BANK, LTD.",
        "phone": "",
        "website": "",
        "country_code": "NP",
        "country_code_alpha3": "NPL",
        "country_name": "NEPAL"
    },
    {
        "bin": "408833",
        "brand": "VISA",
        "type": "DEBIT",
        "category": "CLASSIC",
        "issuer": "JYOTI BIKASH BANK, LTD.",
        "phone": "",
        "website": "",
        "country_code": "NP",
        "country_code_alpha3": "NPL",
        "country_name": "NEPAL"
    },
    {
        "bin": "408910",
        "brand": "VISA",
        "type": "DEBIT",
        "category": "CLASSIC",
        "issuer": "NMB BANK, LTD.",
        "phone": "",
        "website": "http://www.nmbz.co.zw",
        "country_code": "NP",
        "country_code_alpha3": "NPL",
        "country_name": "NEPAL"
    },
    {
        "bin": "408911",
        "brand": "VISA",
        "type": "DEBIT",
        "category": "CLASSIC",
        "issuer": "NMB BANK, LTD.",
        "phone": "",
        "website": "http://www.nmbz.co.zw",
        "country_code": "NP",
        "country_code_alpha3": "NPL",
        "country_name": "NEPAL"
    },
    {
        "bin": "408925",
        "brand": "VISA",
        "type": "DEBIT",
        "category": "CLASSIC",
        "issuer": "NEPAL BANK",
        "phone": "",
        "website": "",
        "country_code": "NP",
        "country_code_alpha3": "NPL",
        "country_name": "NEPAL"
    },
    {
        "bin": "408927",
        "brand": "VISA",
        "type": "DEBIT",
        "category": "CLASSIC",
        "issuer": "NEPAL BANK",
        "phone": "",
        "website": "",
        "country_code": "NP",
        "country_code_alpha3": "NPL",
        "country_name": "NEPAL"
    },
    {
        "bin": "409072",
        "brand": "VISA",
        "type": "DEBIT",
        "category": "CLASSIC",
        "issuer": "PRABHU BANK LTD.",
        "phone": "",
        "website": "",
        "country_code": "NP",
        "country_code_alpha3": "NPL",
        "country_name": "NEPAL"
    },
    {
        "bin": "409506",
        "brand": "VISA",
        "type": "CREDIT",
        "category": "CLASSIC",
        "issuer": "",
        "phone": "",
        "website": "",
        "country_code": "NP",
        "country_code_alpha3": "NPL",
        "country_name": "NEPAL"
    },
    {
        "bin": "410102",
        "brand": "VISA",
        "type": "DEBIT",
        "category": "PREPAID CLASSIC",
        "issuer": "HIMALAYAN BANK, LTD.",
        "phone": "",
        "website": "http://www.himalayanbank.com",
        "country_code": "NP",
        "country_code_alpha3": "NPL",
        "country_name": "NEPAL"
    },
    {
        "bin": "410148",
        "brand": "VISA",
        "type": "DEBIT",
        "category": "CLASSIC",
        "issuer": "HIMALAYAN BANK, LTD.",
        "phone": "+97714227749",
        "website": "http://www.himalayanbank.com",
        "country_code": "NP",
        "country_code_alpha3": "NPL",
        "country_name": "NEPAL"
    },
    {
        "bin": "410149",
        "brand": "VISA",
        "type": "DEBIT",
        "category": "CLASSIC",
        "issuer": "HIMALAYAN BANK, LTD.",
        "phone": "",
        "website": "http://www.himalayanbank.com",
        "country_code": "NP",
        "country_code_alpha3": "NPL",
        "country_name": "NEPAL"
    },
    {
        "bin": "410744",
        "brand": "VISA",
        "type": "DEBIT",
        "category": "PREPAID ELECTRON",
        "issuer": "STANDARD CHARTERED BANK",
        "phone": "+97771524029",
        "website": "https://www.sc.com",
        "country_code": "NP",
        "country_code_alpha3": "NPL",
        "country_name": "NEPAL"
    },
    {
        "bin": "411655",
        "brand": "VISA",
        "type": "DEBIT",
        "category": "CLASSIC",
        "issuer": "LAXMI SUNRISE BANK, LTD.",
        "phone": "",
        "website": "",
        "country_code": "NP",
        "country_code_alpha3": "NPL",
        "country_name": "NEPAL"
    },
    {
        "bin": "412334",
        "brand": "VISA",
        "type": "DEBIT",
        "category": "CLASSIC",
        "issuer": "INTL HDQTRS-CENTER OWNED",
        "phone": "",
        "website": "",
        "country_code": "NP",
        "country_code_alpha3": "NPL",
        "country_name": "NEPAL"
    },
    {
        "bin": "412335",
        "brand": "VISA",
        "type": "CREDIT",
        "category": "CLASSIC",
        "issuer": "INTL HDQTRS-CENTER OWNED",
        "phone": "",
        "website": "",
        "country_code": "NP",
        "country_code_alpha3": "NPL",
        "country_name": "NEPAL"
    },
    {
        "bin": "413545",
        "brand": "VISA",
        "type": "DEBIT",
        "category": "CLASSIC",
        "issuer": "NABIL BANK LTD.",
        "phone": "",
        "website": "",
        "country_code": "NP",
        "country_code_alpha3": "NPL",
        "country_name": "NEPAL"
    },
    {
        "bin": "415433",
        "brand": "VISA",
        "type": "DEBIT",
        "category": "CLASSIC",
        "issuer": "EXCEL DEVELOPMENT BANK, LTD.",
        "phone": "",
        "website": "",
        "country_code": "NP",
        "country_code_alpha3": "NPL",
        "country_name": "NEPAL"
    },
    {
        "bin": "416211",
        "brand": "VISA",
        "type": "DEBIT",
        "category": "CLASSIC",
        "issuer": "LAXMI SUNRISE BANK, LTD.",
        "phone": "",
        "website": "",
        "country_code": "NP",
        "country_code_alpha3": "NPL",
        "country_name": "NEPAL"
    },
    {
        "bin": "416212",
        "brand": "VISA",
        "type": "DEBIT",
        "category": "CLASSIC",
        "issuer": "LAXMI SUNRISE BANK, LTD.",
        "phone": "",
        "website": "",
        "country_code": "NP",
        "country_code_alpha3": "NPL",
        "country_name": "NEPAL"
    },
    {
        "bin": "416213",
        "brand": "VISA",
        "type": "CREDIT",
        "category": "CLASSIC",
        "issuer": "LAXMI SUNRISE BANK, LTD.",
        "phone": "",
        "website": "",
        "country_code": "NP",
        "country_code_alpha3": "NPL",
        "country_name": "NEPAL"
    },
    {
        "bin": "418119",
        "brand": "VISA",
        "type": "DEBIT",
        "category": "",
        "issuer": "RASTRIYA BANIJYA BANK",
        "phone": "",
        "website": "",
        "country_code": "NP",
        "country_code_alpha3": "NPL",
        "country_name": "NEPAL"
    },
    {
        "bin": "418120",
        "brand": "VISA",
        "type": "DEBIT",
        "category": "ELECTRON",
        "issuer": "RASTRIYA BANIJYA BANK",
        "phone": "",
        "website": "",
        "country_code": "NP",
        "country_code_alpha3": "NPL",
        "country_name": "NEPAL"
    },
    {
        "bin": "418121",
        "brand": "VISA",
        "type": "DEBIT",
        "category": "ELECTRON",
        "issuer": "RASTRIYA BANIJYA BANK",
        "phone": "",
        "website": "",
        "country_code": "NP",
        "country_code_alpha3": "NPL",
        "country_name": "NEPAL"
    },
    {
        "bin": "418240",
        "brand": "VISA",
        "type": "DEBIT",
        "category": "CLASSIC",
        "issuer": "LAXMI SUNRISE BANK, LTD.",
        "phone": "",
        "website": "",
        "country_code": "NP",
        "country_code_alpha3": "NPL",
        "country_name": "NEPAL"
    },
    {
        "bin": "418565",
        "brand": "VISA",
        "type": "CREDIT",
        "category": "CLASSIC",
        "issuer": "PRIME COMMERCIAL BANK, LTD.",
        "phone": "",
        "website": "",
        "country_code": "NP",
        "country_code_alpha3": "NPL",
        "country_name": "NEPAL"
    },
    {
        "bin": "418902",
        "brand": "VISA",
        "type": "DEBIT",
        "category": "",
        "issuer": "NABIL BANK, LTD.",
        "phone": "(804) 222-1307",
        "website": "",
        "country_code": "NP",
        "country_code_alpha3": "NPL",
        "country_name": "NEPAL"
    },
    {
        "bin": "419816",
        "brand": "VISA",
        "type": "CREDIT",
        "category": "CORPORATE T&E",
        "issuer": "NMB BANK, LTD.",
        "phone": "",
        "website": "http://www.nmbz.co.zw",
        "country_code": "NP",
        "country_code_alpha3": "NPL",
        "country_name": "NEPAL"
    },
    {
        "bin": "420611",
        "brand": "VISA",
        "type": "CREDIT",
        "category": "CLASSIC",
        "issuer": "KUMARI BANK, LTD.",
        "phone": "",
        "website": "http://www.kumaribank.com",
        "country_code": "NP",
        "country_code_alpha3": "NPL",
        "country_name": "NEPAL"
    },
    {
        "bin": "420622",
        "brand": "VISA",
        "type": "CREDIT",
        "category": "CLASSIC",
        "issuer": "KUMARI BANK, LTD.",
        "phone": "",
        "website": "http://www.kumaribank.com",
        "country_code": "NP",
        "country_code_alpha3": "NPL",
        "country_name": "NEPAL"
    },
    {
        "bin": "420792",
        "brand": "VISA",
        "type": "DEBIT",
        "category": "PREPAID CLASSIC",
        "issuer": "GLOBAL IME BANK, LTD.",
        "phone": "",
        "website": "",
        "country_code": "NP",
        "country_code_alpha3": "NPL",
        "country_name": "NEPAL"
    },
    {
        "bin": "421104",
        "brand": "VISA",
        "type": "CREDIT",
        "category": "",
        "issuer": "STANDARD CHARTERED BANK",
        "phone": "+97771524029",
        "website": "https://www.sc.com",
        "country_code": "NP",
        "country_code_alpha3": "NPL",
        "country_name": "NEPAL"
    },
    {
        "bin": "421105",
        "brand": "VISA",
        "type": "CREDIT",
        "category": "GOLD",
        "issuer": "NEPAL INVESTMENT MEGA BANK, LTD.",
        "phone": "",
        "website": "",
        "country_code": "NP",
        "country_code_alpha3": "NPL",
        "country_name": "NEPAL"
    },
    {
        "bin": "421404",
        "brand": "VISA",
        "type": "DEBIT",
        "category": "PREPAID ELECTRON",
        "issuer": "NEPAL INVESTMENT BANK, LTD.",
        "phone": "",
        "website": "http://www.nibl.com.np",
        "country_code": "NP",
        "country_code_alpha3": "NPL",
        "country_name": "NEPAL"
    },
    {
        "bin": "421406",
        "brand": "VISA",
        "type": "DEBIT",
        "category": "PREPAID ELECTRON",
        "issuer": "NEPAL INVESTMENT MEGA BANK, LTD.",
        "phone": "",
        "website": "",
        "country_code": "NP",
        "country_code_alpha3": "NPL",
        "country_name": "NEPAL"
    },
    {
        "bin": "421411",
        "brand": "VISA",
        "type": "CREDIT",
        "category": "GOLD",
        "issuer": "NEPAL INVESTMENT MEGA BANK, LTD.",
        "phone": "",
        "website": "",
        "country_code": "NP",
        "country_code_alpha3": "NPL",
        "country_name": "NEPAL"
    },
    {
        "bin": "421412",
        "brand": "VISA",
        "type": "CREDIT",
        "category": "GOLD",
        "issuer": "NEPAL INVESTMENT MEGA BANK, LTD.",
        "phone": "",
        "website": "",
        "country_code": "NP",
        "country_code_alpha3": "NPL",
        "country_name": "NEPAL"
    },
    {
        "bin": "421414",
        "brand": "VISA",
        "type": "DEBIT",
        "category": "ELECTRON",
        "issuer": "NEPAL INVESTMENT MEGA BANK, LTD.",
        "phone": "",
        "website": "",
        "country_code": "NP",
        "country_code_alpha3": "NPL",
        "country_name": "NEPAL"
    },
    {
        "bin": "421415",
        "brand": "VISA",
        "type": "DEBIT",
        "category": "ELECTRON",
        "issuer": "NEPAL INVESTMENT MEGA BANK, LTD.",
        "phone": "",
        "website": "",
        "country_code": "NP",
        "country_code_alpha3": "NPL",
        "country_name": "NEPAL"
    },
    {
        "bin": "421416",
        "brand": "VISA",
        "type": "CREDIT",
        "category": "CLASSIC",
        "issuer": "NEPAL INVESTMENT MEGA BANK, LTD.",
        "phone": "",
        "website": "",
        "country_code": "NP",
        "country_code_alpha3": "NPL",
        "country_name": "NEPAL"
    },
    {
        "bin": "422306",
        "brand": "VISA",
        "type": "CREDIT",
        "category": "CLASSIC",
        "issuer": "NEPAL BANGLADESH BANK, LTD.",
        "phone": "",
        "website": "",
        "country_code": "NP",
        "country_code_alpha3": "NPL",
        "country_name": "NEPAL"
    },
    {
        "bin": "422310",
        "brand": "VISA",
        "type": "CREDIT",
        "category": "CLASSIC",
        "issuer": "",
        "phone": "",
        "website": "",
        "country_code": "NP",
        "country_code_alpha3": "NPL",
        "country_name": "NEPAL"
    },
    {
        "bin": "422462",
        "brand": "VISA",
        "type": "DEBIT",
        "category": "CLASSIC",
        "issuer": "",
        "phone": "",
        "website": "",
        "country_code": "NP",
        "country_code_alpha3": "NPL",
        "country_name": "NEPAL"
    },
    {
        "bin": "422476",
        "brand": "VISA",
        "type": "DEBIT",
        "category": "CLASSIC",
        "issuer": "MUKTINATH BIKAS BANK, LTD.",
        "phone": "",
        "website": "",
        "country_code": "NP",
        "country_code_alpha3": "NPL",
        "country_name": "NEPAL"
    },
    {
        "bin": "422592",
        "brand": "VISA",
        "type": "DEBIT",
        "category": "CLASSIC",
        "issuer": "LUMBINI BIKAS BANK, LTD.",
        "phone": "",
        "website": "",
        "country_code": "NP",
        "country_code_alpha3": "NPL",
        "country_name": "NEPAL"
    },
    {
        "bin": "422627",
        "brand": "VISA",
        "type": "DEBIT",
        "category": "ELECTRON",
        "issuer": "NABIL BANK, LTD.",
        "phone": "(804) 222-1307",
        "website": "",
        "country_code": "NP",
        "country_code_alpha3": "NPL",
        "country_name": "NEPAL"
    },
    {
        "bin": "422692",
        "brand": "VISA",
        "type": "DEBIT",
        "category": "CLASSIC",
        "issuer": "",
        "phone": "",
        "website": "",
        "country_code": "NP",
        "country_code_alpha3": "NPL",
        "country_name": "NEPAL"
    },
    {
        "bin": "422705",
        "brand": "VISA",
        "type": "DEBIT",
        "category": "CLASSIC",
        "issuer": "GARIMA BIKAS BANK, LTD.",
        "phone": "",
        "website": "",
        "country_code": "NP",
        "country_code_alpha3": "NPL",
        "country_name": "NEPAL"
    },
    {
        "bin": "423274",
        "brand": "VISA",
        "type": "CREDIT",
        "category": "CLASSIC",
        "issuer": "GLOBAL IME BANK, LTD.",
        "phone": "",
        "website": "",
        "country_code": "NP",
        "country_code_alpha3": "NPL",
        "country_name": "NEPAL"
    },
    {
        "bin": "423276",
        "brand": "VISA",
        "type": "DEBIT",
        "category": "CLASSIC",
        "issuer": "GLOBAL IME BANK, LTD.",
        "phone": "",
        "website": "",
        "country_code": "NP",
        "country_code_alpha3": "NPL",
        "country_name": "NEPAL"
    },
    {
        "bin": "423298",
        "brand": "VISA",
        "type": "DEBIT",
        "category": "CLASSIC",
        "issuer": "GLOBAL IME BANK, LTD.",
        "phone": "",
        "website": "",
        "country_code": "NP",
        "country_code_alpha3": "NPL",
        "country_name": "NEPAL"
    },
    {
        "bin": "423377",
        "brand": "VISA",
        "type": "DEBIT",
        "category": "CLASSIC",
        "issuer": "",
        "phone": "",
        "website": "",
        "country_code": "NP",
        "country_code_alpha3": "NPL",
        "country_name": "NEPAL"
    },
    {
        "bin": "423510",
        "brand": "VISA",
        "type": "DEBIT",
        "category": "PREPAID CLASSIC",
        "issuer": "NIC ASIA BANK, LTD.",
        "phone": "",
        "website": "",
        "country_code": "NP",
        "country_code_alpha3": "NPL",
        "country_name": "NEPAL"
    },
    {
        "bin": "423559",
        "brand": "VISA",
        "type": "DEBIT",
        "category": "CLASSIC",
        "issuer": "NIC ASIA BANK, LTD.",
        "phone": "",
        "website": "",
        "country_code": "NP",
        "country_code_alpha3": "NPL",
        "country_name": "NEPAL"
    },
    {
        "bin": "423567",
        "brand": "VISA",
        "type": "CREDIT",
        "category": "CLASSIC",
        "issuer": "NIC ASIA BANK, LTD.",
        "phone": "",
        "website": "",
        "country_code": "NP",
        "country_code_alpha3": "NPL",
        "country_name": "NEPAL"
    },
    {
        "bin": "424972",
        "brand": "VISA",
        "type": "CREDIT",
        "category": "GOLD",
        "issuer": "NEPAL INVESTMENT MEGA BANK, LTD.",
        "phone": "",
        "website": "",
        "country_code": "NP",
        "country_code_alpha3": "NPL",
        "country_name": "NEPAL"
    },
    {
        "bin": "426501",
        "brand": "VISA",
        "type": "CREDIT",
        "category": "PLATINUM",
        "issuer": "LAXMI SUNRISE BANK, LTD.",
        "phone": "",
        "website": "",
        "country_code": "NP",
        "country_code_alpha3": "NPL",
        "country_name": "NEPAL"
    },
    {
        "bin": "427142",
        "brand": "VISA",
        "type": "DEBIT",
        "category": "CLASSIC",
        "issuer": "NABIL BANK LTD.",
        "phone": "",
        "website": "",
        "country_code": "NP",
        "country_code_alpha3": "NPL",
        "country_name": "NEPAL"
    },
    {
        "bin": "428461",
        "brand": "VISA",
        "type": "DEBIT",
        "category": "CLASSIC",
        "issuer": "HIMALAYAN BANK, LTD.",
        "phone": "+97714227749",
        "website": "http://www.himalayanbank.com",
        "country_code": "NP",
        "country_code_alpha3": "NPL",
        "country_name": "NEPAL"
    },
    {
        "bin": "429919",
        "brand": "VISA",
        "type": "CREDIT",
        "category": "CLASSIC",
        "issuer": "NEPAL CREDIT AND COMMERCE BANK, LTD.",
        "phone": "",
        "website": "",
        "country_code": "NP",
        "country_code_alpha3": "NPL",
        "country_name": "NEPAL"
    },
    {
        "bin": "430511",
        "brand": "VISA",
        "type": "CREDIT",
        "category": "CLASSIC",
        "issuer": "PRABHU BANK LTD.",
        "phone": "",
        "website": "",
        "country_code": "NP",
        "country_code_alpha3": "NPL",
        "country_name": "NEPAL"
    },
    {
        "bin": "430519",
        "brand": "VISA",
        "type": "CREDIT",
        "category": "GOLD",
        "issuer": "PRABHU BANK LTD.",
        "phone": "",
        "website": "",
        "country_code": "NP",
        "country_code_alpha3": "NPL",
        "country_name": "NEPAL"
    },
    {
        "bin": "430543",
        "brand": "VISA",
        "type": "DEBIT",
        "category": "CLASSIC",
        "issuer": "PRABHU BANK LTD.",
        "phone": "",
        "website": "",
        "country_code": "NP",
        "country_code_alpha3": "NPL",
        "country_name": "NEPAL"
    },
    {
        "bin": "430715",
        "brand": "VISA",
        "type": "DEBIT",
        "category": "CLASSIC",
        "issuer": "NEPAL INVESTMENT MEGA BANK, LTD.",
        "phone": "",
        "website": "",
        "country_code": "NP",
        "country_code_alpha3": "NPL",
        "country_name": "NEPAL"
    },
    {
        "bin": "430719",
        "brand": "VISA",
        "type": "DEBIT",
        "category": "CLASSIC",
        "issuer": "NEPAL INVESTMENT MEGA BANK, LTD.",
        "phone": "",
        "website": "",
        "country_code": "NP",
        "country_code_alpha3": "NPL",
        "country_name": "NEPAL"
    },
    {
        "bin": "430724",
        "brand": "VISA",
        "type": "CREDIT",
        "category": "CLASSIC",
        "issuer": "",
        "phone": "",
        "website": "",
        "country_code": "NP",
        "country_code_alpha3": "NPL",
        "country_name": "NEPAL"
    },
    {
        "bin": "430728",
        "brand": "VISA",
        "type": "CREDIT",
        "category": "CLASSIC",
        "issuer": "NEPAL INVESTMENT MEGA BANK, LTD.",
        "phone": "",
        "website": "",
        "country_code": "NP",
        "country_code_alpha3": "NPL",
        "country_name": "NEPAL"
    },
    {
        "bin": "430790",
        "brand": "VISA",
        "type": "DEBIT",
        "category": "CLASSIC",
        "issuer": "MAHALAXMI BIKAS BANK, LTD.",
        "phone": "",
        "website": "",
        "country_code": "NP",
        "country_code_alpha3": "NPL",
        "country_name": "NEPAL"
    },
    {
        "bin": "431792",
        "brand": "VISA",
        "type": "CREDIT",
        "category": "CLASSIC",
        "issuer": "PRIME COMMERCIAL BANK, LTD.",
        "phone": "",
        "website": "",
        "country_code": "NP",
        "country_code_alpha3": "NPL",
        "country_name": "NEPAL"
    },
    {
        "bin": "432946",
        "brand": "VISA",
        "type": "DEBIT",
        "category": "CLASSIC",
        "issuer": "SHINE RESUNGA DEVELOPMENT BANK, LTD.",
        "phone": "",
        "website": "",
        "country_code": "NP",
        "country_code_alpha3": "NPL",
        "country_name": "NEPAL"
    },
    {
        "bin": "433474",
        "brand": "VISA",
        "type": "CREDIT",
        "category": "CLASSIC",
        "issuer": "NEPAL BANK",
        "phone": "",
        "website": "",
        "country_code": "NP",
        "country_code_alpha3": "NPL",
        "country_name": "NEPAL"
    },
    {
        "bin": "433621",
        "brand": "VISA",
        "type": "DEBIT",
        "category": "ELECTRON",
        "issuer": "NEPAL INVESTMENT BANK, LTD.",
        "phone": "+97714228229",
        "website": "http://www.nibl.com.np",
        "country_code": "NP",
        "country_code_alpha3": "NPL",
        "country_name": "NEPAL"
    },
    {
        "bin": "433949",
        "brand": "VISA",
        "type": "DEBIT",
        "category": "CLASSIC",
        "issuer": "",
        "phone": "",
        "website": "",
        "country_code": "NP",
        "country_code_alpha3": "NPL",
        "country_name": "NEPAL"
    },
    {
        "bin": "435978",
        "brand": "VISA",
        "type": "DEBIT",
        "category": "CLASSIC",
        "issuer": "NEPAL SBI BANK, LTD.",
        "phone": "",
        "website": "",
        "country_code": "NP",
        "country_code_alpha3": "NPL",
        "country_name": "NEPAL"
    },
    {
        "bin": "436362",
        "brand": "VISA",
        "type": "DEBIT",
        "category": "",
        "issuer": "HIMALAYAN BANK, LTD.",
        "phone": "+97714227749",
        "website": "http://www.himalayanbank.com",
        "country_code": "NP",
        "country_code_alpha3": "NPL",
        "country_name": "NEPAL"
    },
    {
        "bin": "436439",
        "brand": "VISA",
        "type": "CREDIT",
        "category": "CLASSIC",
        "issuer": "NEPAL INVESTMENT BANK, LTD.",
        "phone": "+97714228229",
        "website": "http://www.nibl.com.np",
        "country_code": "NP",
        "country_code_alpha3": "NPL",
        "country_name": "NEPAL"
    },
    {
        "bin": "436440",
        "brand": "VISA",
        "type": "CREDIT",
        "category": "",
        "issuer": "",
        "phone": "",
        "website": "",
        "country_code": "NP",
        "country_code_alpha3": "NPL",
        "country_name": "NEPAL"
    },
    {
        "bin": "436441",
        "brand": "VISA",
        "type": "CREDIT",
        "category": "GOLD",
        "issuer": "NEPAL INVESTMENT BANK, LTD.",
        "phone": "+97714228229",
        "website": "http://www.nibl.com.np",
        "country_code": "NP",
        "country_code_alpha3": "NPL",
        "country_name": "NEPAL"
    },
    {
        "bin": "436442",
        "brand": "VISA",
        "type": "CREDIT",
        "category": "",
        "issuer": "",
        "phone": "",
        "website": "",
        "country_code": "NP",
        "country_code_alpha3": "NPL",
        "country_name": "NEPAL"
    },
    {
        "bin": "436443",
        "brand": "VISA",
        "type": "DEBIT",
        "category": "CLASSIC",
        "issuer": "NEPAL INVESTMENT BANK, LTD.",
        "phone": "+97714228229",
        "website": "http://www.nibl.com.np",
        "country_code": "NP",
        "country_code_alpha3": "NPL",
        "country_name": "NEPAL"
    },
    {
        "bin": "436444",
        "brand": "VISA",
        "type": "DEBIT",
        "category": "CLASSIC",
        "issuer": "NEPAL INVESTMENT BANK, LTD.",
        "phone": "+97714228229",
        "website": "http://www.nibl.com.np",
        "country_code": "NP",
        "country_code_alpha3": "NPL",
        "country_name": "NEPAL"
    },
    {
        "bin": "436478",
        "brand": "VISA",
        "type": "DEBIT",
        "category": "",
        "issuer": "NEPAL INVESTMENT BANK, LTD.",
        "phone": "+97714228229",
        "website": "http://www.nibl.com.np",
        "country_code": "NP",
        "country_code_alpha3": "NPL",
        "country_name": "NEPAL"
    },
    {
        "bin": "436497",
        "brand": "VISA",
        "type": "DEBIT",
        "category": "PREPAID",
        "issuer": "NEPAL INVESTMENT BANK, LTD.",
        "phone": "+97714228229",
        "website": "http://www.nibl.com.np",
        "country_code": "NP",
        "country_code_alpha3": "NPL",
        "country_name": "NEPAL"
    },
    {
        "bin": "436498",
        "brand": "VISA",
        "type": "DEBIT",
        "category": "PREPAID",
        "issuer": "NEPAL INVESTMENT BANK, LTD.",
        "phone": "+97714228229",
        "website": "http://www.nibl.com.np",
        "country_code": "NP",
        "country_code_alpha3": "NPL",
        "country_name": "NEPAL"
    },
    {
        "bin": "436895",
        "brand": "VISA",
        "type": "DEBIT",
        "category": "CLASSIC",
        "issuer": "GLOBAL IME BANK, LTD.",
        "phone": "",
        "website": "",
        "country_code": "NP",
        "country_code_alpha3": "NPL",
        "country_name": "NEPAL"
    },
    {
        "bin": "437031",
        "brand": "VISA",
        "type": "DEBIT",
        "category": "",
        "issuer": "",
        "phone": "",
        "website": "",
        "country_code": "NP",
        "country_code_alpha3": "NPL",
        "country_name": "NEPAL"
    },
    {
        "bin": "437369",
        "brand": "VISA",
        "type": "DEBIT",
        "category": "CLASSIC",
        "issuer": "LAXMI SUNRISE BANK, LTD.",
        "phone": "",
        "website": "",
        "country_code": "NP",
        "country_code_alpha3": "NPL",
        "country_name": "NEPAL"
    },
    {
        "bin": "437370",
        "brand": "VISA",
        "type": "DEBIT",
        "category": "CLASSIC",
        "issuer": "LAXMI SUNRISE BANK, LTD.",
        "phone": "",
        "website": "",
        "country_code": "NP",
        "country_code_alpha3": "NPL",
        "country_name": "NEPAL"
    },
    {
        "bin": "437371",
        "brand": "VISA",
        "type": "DEBIT",
        "category": "",
        "issuer": "SUNRISE BANK, LTD.",
        "phone": "",
        "website": "",
        "country_code": "NP",
        "country_code_alpha3": "NPL",
        "country_name": "NEPAL"
    },
    {
        "bin": "438093",
        "brand": "VISA",
        "type": "DEBIT",
        "category": "CLASSIC",
        "issuer": "",
        "phone": "",
        "website": "",
        "country_code": "NP",
        "country_code_alpha3": "NPL",
        "country_name": "NEPAL"
    },
    {
        "bin": "438867",
        "brand": "VISA",
        "type": "CREDIT",
        "category": "GOLD",
        "issuer": "",
        "phone": "",
        "website": "",
        "country_code": "NP",
        "country_code_alpha3": "NPL",
        "country_name": "NEPAL"
    },
    {
        "bin": "439076",
        "brand": "VISA",
        "type": "CREDIT",
        "category": "CLASSIC",
        "issuer": "SHINE RESUNGA DEVELOPMENT BANK, LTD.",
        "phone": "",
        "website": "",
        "country_code": "NP",
        "country_code_alpha3": "NPL",
        "country_name": "NEPAL"
    },
    {
        "bin": "439128",
        "brand": "VISA",
        "type": "CREDIT",
        "category": "CLASSIC",
        "issuer": "KUMARI BANK, LTD.",
        "phone": "",
        "website": "http://www.kumaribank.com",
        "country_code": "NP",
        "country_code_alpha3": "NPL",
        "country_name": "NEPAL"
    },
    {
        "bin": "439129",
        "brand": "VISA",
        "type": "DEBIT",
        "category": "ELECTRON",
        "issuer": "KUMARI BANK, LTD.",
        "phone": "",
        "website": "http://www.kumaribank.com",
        "country_code": "NP",
        "country_code_alpha3": "NPL",
        "country_name": "NEPAL"
    },
    {
        "bin": "439274",
        "brand": "VISA",
        "type": "DEBIT",
        "category": "CLASSIC",
        "issuer": "SHANGRI-LA DEVELOPMENT BANK, LTD.",
        "phone": "",
        "website": "",
        "country_code": "NP",
        "country_code_alpha3": "NPL",
        "country_name": "NEPAL"
    },
    {
        "bin": "439371",
        "brand": "VISA",
        "type": "DEBIT",
        "category": "PREPAID ELECTRON",
        "issuer": "NABIL BANK, LTD.",
        "phone": "(804) 222-1307",
        "website": "",
        "country_code": "NP",
        "country_code_alpha3": "NPL",
        "country_name": "NEPAL"
    },
    {
        "bin": "440403",
        "brand": "VISA",
        "type": "DEBIT",
        "category": "PREPAID CLASSIC",
        "issuer": "HIMALAYAN BANK, LTD.",
        "phone": "",
        "website": "http://www.himalayanbank.com",
        "country_code": "NP",
        "country_code_alpha3": "NPL",
        "country_name": "NEPAL"
    },
    {
        "bin": "440404",
        "brand": "VISA",
        "type": "DEBIT",
        "category": "PREPAID GOLD",
        "issuer": "HIMALAYAN BANK, LTD.",
        "phone": "+97714227749",
        "website": "http://www.himalayanbank.com",
        "country_code": "NP",
        "country_code_alpha3": "NPL",
        "country_name": "NEPAL"
    },
    {
        "bin": "440449",
        "brand": "VISA",
        "type": "CREDIT",
        "category": "GOLD",
        "issuer": "HIMALAYAN BANK, LTD.",
        "phone": "",
        "website": "http://www.himalayanbank.com",
        "country_code": "NP",
        "country_code_alpha3": "NPL",
        "country_name": "NEPAL"
    },
    {
        "bin": "440450",
        "brand": "VISA",
        "type": "CREDIT",
        "category": "CLASSIC",
        "issuer": "HIMALAYAN BANK, LTD.",
        "phone": "",
        "website": "http://www.himalayanbank.com",
        "country_code": "NP",
        "country_code_alpha3": "NPL",
        "country_name": "NEPAL"
    },
    {
        "bin": "440467",
        "brand": "VISA",
        "type": "CREDIT",
        "category": "GOLD",
        "issuer": "HIMALAYAN BANK, LTD.",
        "phone": "",
        "website": "http://www.himalayanbank.com",
        "country_code": "NP",
        "country_code_alpha3": "NPL",
        "country_name": "NEPAL"
    },
    {
        "bin": "440468",
        "brand": "VISA",
        "type": "CREDIT",
        "category": "CLASSIC",
        "issuer": "HIMALAYAN BANK, LTD.",
        "phone": "",
        "website": "http://www.himalayanbank.com",
        "country_code": "NP",
        "country_code_alpha3": "NPL",
        "country_name": "NEPAL"
    },
    {
        "bin": "442440",
        "brand": "VISA",
        "type": "DEBIT",
        "category": "PREPAID CLASSIC",
        "issuer": "NEPAL SBI BANK, LTD.",
        "phone": "",
        "website": "",
        "country_code": "NP",
        "country_code_alpha3": "NPL",
        "country_name": "NEPAL"
    },
    {
        "bin": "443083",
        "brand": "VISA",
        "type": "CREDIT",
        "category": "",
        "issuer": "NEPAL DEVELOPMENT BANK, LTD.",
        "phone": "00-977-425-4639",
        "website": "",
        "country_code": "NP",
        "country_code_alpha3": "NPL",
        "country_name": "NEPAL"
    },
    {
        "bin": "443830",
        "brand": "VISA",
        "type": "DEBIT",
        "category": "CLASSIC",
        "issuer": "SIDDHARTHA BANK, LTD.",
        "phone": "",
        "website": "",
        "country_code": "NP",
        "country_code_alpha3": "NPL",
        "country_name": "NEPAL"
    },
    {
        "bin": "443832",
        "brand": "VISA",
        "type": "CREDIT",
        "category": "CLASSIC",
        "issuer": "SIDDHARTHA BANK, LTD.",
        "phone": "",
        "website": "",
        "country_code": "NP",
        "country_code_alpha3": "NPL",
        "country_name": "NEPAL"
    },
    {
        "bin": "443834",
        "brand": "VISA",
        "type": "DEBIT",
        "category": "PREPAID CLASSIC",
        "issuer": "SIDDHARTHA BANK, LTD.",
        "phone": "",
        "website": "",
        "country_code": "NP",
        "country_code_alpha3": "NPL",
        "country_name": "NEPAL"
    },
    {
        "bin": "445631",
        "brand": "VISA",
        "type": "DEBIT",
        "category": "CLASSIC",
        "issuer": "NEPAL INVESTMENT MEGA BANK, LTD.",
        "phone": "",
        "website": "",
        "country_code": "NP",
        "country_code_alpha3": "NPL",
        "country_name": "NEPAL"
    },
    {
        "bin": "445698",
        "brand": "VISA",
        "type": "DEBIT",
        "category": "PREPAID CLASSIC",
        "issuer": "AGRICULTURAL DEVELOPMENT BANK, LTD.",
        "phone": "",
        "website": "",
        "country_code": "NP",
        "country_code_alpha3": "NPL",
        "country_name": "NEPAL"
    },
    {
        "bin": "450052",
        "brand": "VISA",
        "type": "DEBIT",
        "category": "PREPAID CLASSIC",
        "issuer": "SANIMA BANK, LTD.",
        "phone": "",
        "website": "",
        "country_code": "NP",
        "country_code_alpha3": "NPL",
        "country_name": "NEPAL"
    },
    {
        "bin": "450485",
        "brand": "VISA",
        "type": "CREDIT",
        "category": "CLASSIC",
        "issuer": "NEPAL BANGLADESH BANK, LTD.",
        "phone": "",
        "website": "",
        "country_code": "NP",
        "country_code_alpha3": "NPL",
        "country_name": "NEPAL"
    },
    {
        "bin": "450486",
        "brand": "VISA",
        "type": "CREDIT",
        "category": "CLASSIC",
        "issuer": "NEPAL BANGLADESH BANK, LTD.",
        "phone": "",
        "website": "",
        "country_code": "NP",
        "country_code_alpha3": "NPL",
        "country_name": "NEPAL"
    },
    {
        "bin": "451132",
        "brand": "VISA",
        "type": "CREDIT",
        "category": "CLASSIC",
        "issuer": "NABIL BANK LTD.",
        "phone": "",
        "website": "",
        "country_code": "NP",
        "country_code_alpha3": "NPL",
        "country_name": "NEPAL"
    },
    {
        "bin": "452065",
        "brand": "VISA",
        "type": "DEBIT",
        "category": "CLASSIC",
        "issuer": "CITIZENS BANK INTERNATIONAL, LTD.",
        "phone": "",
        "website": "",
        "country_code": "NP",
        "country_code_alpha3": "NPL",
        "country_name": "NEPAL"
    },
    {
        "bin": "455269",
        "brand": "VISA",
        "type": "DEBIT",
        "category": "CLASSIC",
        "issuer": "",
        "phone": "",
        "website": "",
        "country_code": "NP",
        "country_code_alpha3": "NPL",
        "country_name": "NEPAL"
    },
    {
        "bin": "456597",
        "brand": "VISA",
        "type": "DEBIT",
        "category": "BUSINESS",
        "issuer": "PRABHU BANK LTD.",
        "phone": "",
        "website": "",
        "country_code": "NP",
        "country_code_alpha3": "NPL",
        "country_name": "NEPAL"
    },
    {
        "bin": "457412",
        "brand": "VISA",
        "type": "DEBIT",
        "category": "ELECTRON",
        "issuer": "NEPAL SBI BANK, LTD.",
        "phone": "",
        "website": "",
        "country_code": "NP",
        "country_code_alpha3": "NPL",
        "country_name": "NEPAL"
    },
    {
        "bin": "457481",
        "brand": "VISA",
        "type": "DEBIT",
        "category": "CLASSIC",
        "issuer": "STANDARD CHARTERED BANK",
        "phone": "+97771524029",
        "website": "https://www.sc.com",
        "country_code": "NP",
        "country_code_alpha3": "NPL",
        "country_name": "NEPAL"
    },
    {
        "bin": "457484",
        "brand": "VISA",
        "type": "DEBIT",
        "category": "PLATINUM",
        "issuer": "STANDARD CHARTERED BANK",
        "phone": "+97771524029",
        "website": "https://www.sc.com",
        "country_code": "NP",
        "country_code_alpha3": "NPL",
        "country_name": "NEPAL"
    },
    {
        "bin": "457709",
        "brand": "VISA",
        "type": "DEBIT",
        "category": "CLASSIC",
        "issuer": "SUNRISE BANK, LTD.",
        "phone": "",
        "website": "",
        "country_code": "NP",
        "country_code_alpha3": "NPL",
        "country_name": "NEPAL"
    },
    {
        "bin": "457987",
        "brand": "VISA",
        "type": "CREDIT",
        "category": "CLASSIC",
        "issuer": "NABIL BANK LTD.",
        "phone": "",
        "website": "",
        "country_code": "NP",
        "country_code_alpha3": "NPL",
        "country_name": "NEPAL"
    },
    {
        "bin": "458172",
        "brand": "VISA",
        "type": "DEBIT",
        "category": "CLASSIC",
        "issuer": "NEPAL INVESTMENT MEGA BANK, LTD.",
        "phone": "",
        "website": "",
        "country_code": "NP",
        "country_code_alpha3": "NPL",
        "country_name": "NEPAL"
    },
    {
        "bin": "458701",
        "brand": "VISA",
        "type": "DEBIT",
        "category": "CLASSIC",
        "issuer": "NABIL BANK LTD.",
        "phone": "",
        "website": "",
        "country_code": "NP",
        "country_code_alpha3": "NPL",
        "country_name": "NEPAL"
    },
    {
        "bin": "459521",
        "brand": "VISA",
        "type": "DEBIT",
        "category": "CLASSIC",
        "issuer": "CITIZENS BANK INTERNATIONAL, LTD.",
        "phone": "",
        "website": "",
        "country_code": "NP",
        "country_code_alpha3": "NPL",
        "country_name": "NEPAL"
    },
    {
        "bin": "459522",
        "brand": "VISA",
        "type": "CREDIT",
        "category": "",
        "issuer": "CITIZENS BANK INTERNATIONAL, LTD.",
        "phone": "",
        "website": "",
        "country_code": "NP",
        "country_code_alpha3": "NPL",
        "country_name": "NEPAL"
    },
    {
        "bin": "459550",
        "brand": "VISA",
        "type": "CREDIT",
        "category": "",
        "issuer": "",
        "phone": "",
        "website": "",
        "country_code": "NP",
        "country_code_alpha3": "NPL",
        "country_name": "NEPAL"
    },
    {
        "bin": "461003",
        "brand": "VISA",
        "type": "CREDIT",
        "category": "CLASSIC",
        "issuer": "SANIMA BANK, LTD.",
        "phone": "",
        "website": "",
        "country_code": "NP",
        "country_code_alpha3": "NPL",
        "country_name": "NEPAL"
    },
    {
        "bin": "461004",
        "brand": "VISA",
        "type": "DEBIT",
        "category": "CLASSIC",
        "issuer": "SANIMA BANK, LTD.",
        "phone": "",
        "website": "",
        "country_code": "NP",
        "country_code_alpha3": "NPL",
        "country_name": "NEPAL"
    },
    {
        "bin": "461005",
        "brand": "VISA",
        "type": "DEBIT",
        "category": "CLASSIC",
        "issuer": "SANIMA BANK, LTD.",
        "phone": "",
        "website": "",
        "country_code": "NP",
        "country_code_alpha3": "NPL",
        "country_name": "NEPAL"
    },
    {
        "bin": "461006",
        "brand": "VISA",
        "type": "DEBIT",
        "category": "PREPAID",
        "issuer": "SANIMA BANK, LTD.",
        "phone": "",
        "website": "",
        "country_code": "NP",
        "country_code_alpha3": "NPL",
        "country_name": "NEPAL"
    },
    {
        "bin": "461743",
        "brand": "VISA",
        "type": "CREDIT",
        "category": "CLASSIC",
        "issuer": "STANDARD CHARTERED BANK",
        "phone": "+97771524029",
        "website": "https://www.sc.com",
        "country_code": "NP",
        "country_code_alpha3": "NPL",
        "country_name": "NEPAL"
    },
    {
        "bin": "461993",
        "brand": "VISA",
        "type": "CREDIT",
        "category": "GOLD",
        "issuer": "GLOBAL IME BANK, LTD.",
        "phone": "",
        "website": "",
        "country_code": "NP",
        "country_code_alpha3": "NPL",
        "country_name": "NEPAL"
    },
    {
        "bin": "461994",
        "brand": "VISA",
        "type": "DEBIT",
        "category": "CLASSIC",
        "issuer": "GLOBAL IME BANK, LTD.",
        "phone": "",
        "website": "",
        "country_code": "NP",
        "country_code_alpha3": "NPL",
        "country_name": "NEPAL"
    },
    {
        "bin": "462261",
        "brand": "VISA",
        "type": "CREDIT",
        "category": "CLASSIC",
        "issuer": "BANK OF KATHMANDU, LTD.",
        "phone": "+97714414541 / +97714701201",
        "website": "http://www.bok.com.np",
        "country_code": "NP",
        "country_code_alpha3": "NPL",
        "country_name": "NEPAL"
    },
    {
        "bin": "462262",
        "brand": "VISA",
        "type": "DEBIT",
        "category": "CLASSIC",
        "issuer": "BANK OF KATHMANDU, LTD.",
        "phone": "+97714414541 / +97714701201",
        "website": "http://www.bok.com.np",
        "country_code": "NP",
        "country_code_alpha3": "NPL",
        "country_name": "NEPAL"
    },
    {
        "bin": "462416",
        "brand": "VISA",
        "type": "DEBIT",
        "category": "CLASSIC",
        "issuer": "NEPAL CREDIT AND COMMERCE BANK, LTD.",
        "phone": "",
        "website": "",
        "country_code": "NP",
        "country_code_alpha3": "NPL",
        "country_name": "NEPAL"
    },
    {
        "bin": "462470",
        "brand": "VISA",
        "type": "DEBIT",
        "category": "CLASSIC",
        "issuer": "NEPAL BANGLADESH BANK, LTD.",
        "phone": "",
        "website": "",
        "country_code": "NP",
        "country_code_alpha3": "NPL",
        "country_name": "NEPAL"
    },
    {
        "bin": "462471",
        "brand": "VISA",
        "type": "DEBIT",
        "category": "CLASSIC",
        "issuer": "NEPAL BANGLADESH BANK, LTD.",
        "phone": "",
        "website": "",
        "country_code": "NP",
        "country_code_alpha3": "NPL",
        "country_name": "NEPAL"
    },
    {
        "bin": "463724",
        "brand": "VISA",
        "type": "DEBIT",
        "category": "PREPAID CLASSIC",
        "issuer": "JYOTI BIKASH BANK, LTD.",
        "phone": "",
        "website": "",
        "country_code": "NP",
        "country_code_alpha3": "NPL",
        "country_name": "NEPAL"
    },
    {
        "bin": "463725",
        "brand": "VISA",
        "type": "CREDIT",
        "category": "CLASSIC",
        "issuer": "MAHALAXMI BIKAS BANK, LTD.",
        "phone": "",
        "website": "",
        "country_code": "NP",
        "country_code_alpha3": "NPL",
        "country_name": "NEPAL"
    },
    {
        "bin": "463726",
        "brand": "VISA",
        "type": "CREDIT",
        "category": "PLATINUM",
        "issuer": "SIDDHARTHA BANK, LTD.",
        "phone": "",
        "website": "",
        "country_code": "NP",
        "country_code_alpha3": "NPL",
        "country_name": "NEPAL"
    },
    {
        "bin": "464500",
        "brand": "VISA",
        "type": "DEBIT",
        "category": "CLASSIC",
        "issuer": "",
        "phone": "",
        "website": "",
        "country_code": "NP",
        "country_code_alpha3": "NPL",
        "country_name": "NEPAL"
    },
    {
        "bin": "464503",
        "brand": "VISA",
        "type": "DEBIT",
        "category": "CLASSIC",
        "issuer": "",
        "phone": "",
        "website": "",
        "country_code": "NP",
        "country_code_alpha3": "NPL",
        "country_name": "NEPAL"
    },
    {
        "bin": "465755",
        "brand": "VISA",
        "type": "DEBIT",
        "category": "",
        "issuer": "",
        "phone": "",
        "website": "",
        "country_code": "NP",
        "country_code_alpha3": "NPL",
        "country_name": "NEPAL"
    },
    {
        "bin": "466042",
        "brand": "VISA",
        "type": "DEBIT",
        "category": "CLASSIC",
        "issuer": "PRABHU BANK LTD.",
        "phone": "",
        "website": "",
        "country_code": "NP",
        "country_code_alpha3": "NPL",
        "country_name": "NEPAL"
    },
    {
        "bin": "466043",
        "brand": "VISA",
        "type": "CREDIT",
        "category": "CLASSIC",
        "issuer": "JYOTI BIKASH BANK, LTD.",
        "phone": "",
        "website": "",
        "country_code": "NP",
        "country_code_alpha3": "NPL",
        "country_name": "NEPAL"
    },
    {
        "bin": "466044",
        "brand": "VISA",
        "type": "CREDIT",
        "category": "CLASSIC",
        "issuer": "PRABHU BANK LTD.",
        "phone": "",
        "website": "",
        "country_code": "NP",
        "country_code_alpha3": "NPL",
        "country_name": "NEPAL"
    },
    {
        "bin": "466045",
        "brand": "VISA",
        "type": "DEBIT",
        "category": "",
        "issuer": "KIST BANK, LTD.",
        "phone": "",
        "website": "",
        "country_code": "NP",
        "country_code_alpha3": "NPL",
        "country_name": "NEPAL"
    },
    {
        "bin": "466046",
        "brand": "VISA",
        "type": "DEBIT",
        "category": "CLASSIC",
        "issuer": "PRABHU BANK LTD.",
        "phone": "",
        "website": "",
        "country_code": "NP",
        "country_code_alpha3": "NPL",
        "country_name": "NEPAL"
    },
    {
        "bin": "466293",
        "brand": "VISA",
        "type": "CREDIT",
        "category": "PLATINUM",
        "issuer": "STANDARD CHARTERED BANK",
        "phone": "+97771524029",
        "website": "https://www.sc.com",
        "country_code": "NP",
        "country_code_alpha3": "NPL",
        "country_name": "NEPAL"
    },
    {
        "bin": "468751",
        "brand": "VISA",
        "type": "CREDIT",
        "category": "CLASSIC",
        "issuer": "GARIMA BIKAS BANK, LTD.",
        "phone": "",
        "website": "",
        "country_code": "NP",
        "country_code_alpha3": "NPL",
        "country_name": "NEPAL"
    },
    {
        "bin": "468950",
        "brand": "VISA",
        "type": "DEBIT",
        "category": "ELECTRON",
        "issuer": "GLOBAL IME BANK, LTD.",
        "phone": "",
        "website": "",
        "country_code": "NP",
        "country_code_alpha3": "NPL",
        "country_name": "NEPAL"
    },
    {
        "bin": "468959",
        "brand": "VISA",
        "type": "DEBIT",
        "category": "ELECTRON",
        "issuer": "NEPAL CREDIT AND COMMERCE BANK, LTD.",
        "phone": "",
        "website": "",
        "country_code": "NP",
        "country_code_alpha3": "NPL",
        "country_name": "NEPAL"
    },
    {
        "bin": "469583",
        "brand": "VISA",
        "type": "DEBIT",
        "category": "PLATINUM",
        "issuer": "SIDDHARTHA BANK, LTD.",
        "phone": "",
        "website": "",
        "country_code": "NP",
        "country_code_alpha3": "NPL",
        "country_name": "NEPAL"
    },
    {
        "bin": "470365",
        "brand": "VISA",
        "type": "DEBIT",
        "category": "CLASSIC",
        "issuer": "KAMANA SEWA BIKAS BANK, LTD.",
        "phone": "",
        "website": "",
        "country_code": "NP",
        "country_code_alpha3": "NPL",
        "country_name": "NEPAL"
    },
    {
        "bin": "470553",
        "brand": "VISA",
        "type": "DEBIT",
        "category": "ELECTRON",
        "issuer": "NEPAL INVESTMENT BANK, LTD.",
        "phone": "+97714228229",
        "website": "http://www.nibl.com.np",
        "country_code": "NP",
        "country_code_alpha3": "NPL",
        "country_name": "NEPAL"
    },
    {
        "bin": "470554",
        "brand": "VISA",
        "type": "DEBIT",
        "category": "ELECTRON",
        "issuer": "MACHHAPUCHCHHRE BANK, LTD.",
        "phone": "",
        "website": "",
        "country_code": "NP",
        "country_code_alpha3": "NPL",
        "country_name": "NEPAL"
    },
    {
        "bin": "470555",
        "brand": "VISA",
        "type": "CREDIT",
        "category": "",
        "issuer": "NEPAL INVESTMENT BANK, LTD.",
        "phone": "+97714228229",
        "website": "http://www.nibl.com.np",
        "country_code": "NP",
        "country_code_alpha3": "NPL",
        "country_name": "NEPAL"
    },
    {
        "bin": "470946",
        "brand": "VISA",
        "type": "CREDIT",
        "category": "CLASSIC",
        "issuer": "NMB BANK, LTD.",
        "phone": "",
        "website": "http://www.nmbz.co.zw",
        "country_code": "NP",
        "country_code_alpha3": "NPL",
        "country_name": "NEPAL"
    },
    {
        "bin": "472363",
        "brand": "VISA",
        "type": "DEBIT",
        "category": "PREPAID",
        "issuer": "",
        "phone": "",
        "website": "",
        "country_code": "NP",
        "country_code_alpha3": "NPL",
        "country_name": "NEPAL"
    },
    {
        "bin": "472387",
        "brand": "VISA",
        "type": "DEBIT",
        "category": "PREPAID CLASSIC",
        "issuer": "EVEREST BANK, LTD.",
        "phone": "",
        "website": "",
        "country_code": "NP",
        "country_code_alpha3": "NPL",
        "country_name": "NEPAL"
    },
    {
        "bin": "474830",
        "brand": "VISA",
        "type": "DEBIT",
        "category": "CLASSIC",
        "issuer": "PRIME COMMERCIAL BANK, LTD.",
        "phone": "",
        "website": "",
        "country_code": "NP",
        "country_code_alpha3": "NPL",
        "country_name": "NEPAL"
    },
    {
        "bin": "474879",
        "brand": "VISA",
        "type": "DEBIT",
        "category": "PREPAID ELECTRON",
        "issuer": "PRIME COMMERCIAL BANK, LTD.",
        "phone": "",
        "website": "",
        "country_code": "NP",
        "country_code_alpha3": "NPL",
        "country_name": "NEPAL"
    },
    {
        "bin": "475396",
        "brand": "VISA",
        "type": "DEBIT",
        "category": "CLASSIC",
        "issuer": "AGRICULTURAL DEVELOPMENT BANK, LTD.",
        "phone": "",
        "website": "",
        "country_code": "NP",
        "country_code_alpha3": "NPL",
        "country_name": "NEPAL"
    },
    {
        "bin": "478675",
        "brand": "VISA",
        "type": "CREDIT",
        "category": "CLASSIC",
        "issuer": "KAMANA SEWA BIKAS BANK, LTD.",
        "phone": "",
        "website": "",
        "country_code": "NP",
        "country_code_alpha3": "NPL",
        "country_name": "NEPAL"
    },
    {
        "bin": "479948",
        "brand": "VISA",
        "type": "CREDIT",
        "category": "CLASSIC",
        "issuer": "",
        "phone": "",
        "website": "",
        "country_code": "NP",
        "country_code_alpha3": "NPL",
        "country_name": "NEPAL"
    },
    {
        "bin": "479949",
        "brand": "VISA",
        "type": "CREDIT",
        "category": "CLASSIC",
        "issuer": "",
        "phone": "",
        "website": "",
        "country_code": "NP",
        "country_code_alpha3": "NPL",
        "country_name": "NEPAL"
    },
    {
        "bin": "479950",
        "brand": "VISA",
        "type": "DEBIT",
        "category": "CLASSIC",
        "issuer": "",
        "phone": "",
        "website": "",
        "country_code": "NP",
        "country_code_alpha3": "NPL",
        "country_name": "NEPAL"
    },
    {
        "bin": "479951",
        "brand": "VISA",
        "type": "DEBIT",
        "category": "CLASSIC",
        "issuer": "NEPAL INVESTMENT MEGA BANK, LTD.",
        "phone": "",
        "website": "",
        "country_code": "NP",
        "country_code_alpha3": "NPL",
        "country_name": "NEPAL"
    },
    {
        "bin": "479955",
        "brand": "VISA",
        "type": "DEBIT",
        "category": "CLASSIC",
        "issuer": "GLOBAL IME BANK, LTD.",
        "phone": "",
        "website": "",
        "country_code": "NP",
        "country_code_alpha3": "NPL",
        "country_name": "NEPAL"
    },
    {
        "bin": "479956",
        "brand": "VISA",
        "type": "DEBIT",
        "category": "PREPAID",
        "issuer": "GLOBAL IME BANK, LTD.",
        "phone": "",
        "website": "",
        "country_code": "NP",
        "country_code_alpha3": "NPL",
        "country_name": "NEPAL"
    },
    {
        "bin": "479958",
        "brand": "VISA",
        "type": "CREDIT",
        "category": "CLASSIC",
        "issuer": "",
        "phone": "",
        "website": "",
        "country_code": "NP",
        "country_code_alpha3": "NPL",
        "country_name": "NEPAL"
    },
    {
        "bin": "479979",
        "brand": "VISA",
        "type": "DEBIT",
        "category": "CLASSIC",
        "issuer": "MAHALAXMI BIKAS BANK, LTD.",
        "phone": "",
        "website": "",
        "country_code": "NP",
        "country_code_alpha3": "NPL",
        "country_name": "NEPAL"
    },
    {
        "bin": "479989",
        "brand": "VISA",
        "type": "DEBIT",
        "category": "CLASSIC",
        "issuer": "",
        "phone": "",
        "website": "",
        "country_code": "NP",
        "country_code_alpha3": "NPL",
        "country_name": "NEPAL"
    },
    {
        "bin": "479990",
        "brand": "VISA",
        "type": "DEBIT",
        "category": "PREPAID",
        "issuer": "",
        "phone": "",
        "website": "",
        "country_code": "NP",
        "country_code_alpha3": "NPL",
        "country_name": "NEPAL"
    },
    {
        "bin": "481364",
        "brand": "VISA",
        "type": "CREDIT",
        "category": "CLASSIC",
        "issuer": "EVEREST BANK, LTD.",
        "phone": "",
        "website": "",
        "country_code": "NP",
        "country_code_alpha3": "NPL",
        "country_name": "NEPAL"
    },
    {
        "bin": "481367",
        "brand": "VISA",
        "type": "DEBIT",
        "category": "CLASSIC",
        "issuer": "EVEREST BANK, LTD.",
        "phone": "",
        "website": "",
        "country_code": "NP",
        "country_code_alpha3": "NPL",
        "country_name": "NEPAL"
    },
    {
        "bin": "483751",
        "brand": "VISA",
        "type": "DEBIT",
        "category": "CLASSIC",
        "issuer": "NMB BANK, LTD.",
        "phone": "",
        "website": "http://www.nmbz.co.zw",
        "country_code": "NP",
        "country_code_alpha3": "NPL",
        "country_name": "NEPAL"
    },
    {
        "bin": "483752",
        "brand": "VISA",
        "type": "DEBIT",
        "category": "CLASSIC",
        "issuer": "NMB BANK, LTD.",
        "phone": "",
        "website": "http://www.nmbz.co.zw",
        "country_code": "NP",
        "country_code_alpha3": "NPL",
        "country_name": "NEPAL"
    },
    {
        "bin": "484814",
        "brand": "VISA",
        "type": "DEBIT",
        "category": "CLASSIC",
        "issuer": "HIMALAYAN BANK, LTD.",
        "phone": "+97714227749",
        "website": "http://www.himalayanbank.com",
        "country_code": "NP",
        "country_code_alpha3": "NPL",
        "country_name": "NEPAL"
    },
    {
        "bin": "484815",
        "brand": "VISA",
        "type": "DEBIT",
        "category": "CLASSIC",
        "issuer": "HIMALAYAN BANK, LTD.",
        "phone": "+97714227749",
        "website": "http://www.himalayanbank.com",
        "country_code": "NP",
        "country_code_alpha3": "NPL",
        "country_name": "NEPAL"
    },
    {
        "bin": "486266",
        "brand": "VISA",
        "type": "CREDIT",
        "category": "CLASSIC",
        "issuer": "GLOBAL IME BANK, LTD.",
        "phone": "",
        "website": "",
        "country_code": "NP",
        "country_code_alpha3": "NPL",
        "country_name": "NEPAL"
    },
    {
        "bin": "486267",
        "brand": "VISA",
        "type": "DEBIT",
        "category": "CLASSIC",
        "issuer": "GLOBAL IME BANK, LTD.",
        "phone": "",
        "website": "",
        "country_code": "NP",
        "country_code_alpha3": "NPL",
        "country_name": "NEPAL"
    },
    {
        "bin": "486268",
        "brand": "VISA",
        "type": "CREDIT",
        "category": "GOLD",
        "issuer": "GLOBAL IME BANK, LTD.",
        "phone": "",
        "website": "",
        "country_code": "NP",
        "country_code_alpha3": "NPL",
        "country_name": "NEPAL"
    },
    {
        "bin": "486278",
        "brand": "VISA",
        "type": "DEBIT",
        "category": "CLASSIC",
        "issuer": "BANK OF KATHMANDU, LTD.",
        "phone": "+97714414541 / +97714701201",
        "website": "http://www.bok.com.np",
        "country_code": "NP",
        "country_code_alpha3": "NPL",
        "country_name": "NEPAL"
    },
    {
        "bin": "489020",
        "brand": "VISA",
        "type": "CREDIT",
        "category": "CLASSIC",
        "issuer": "MACHHAPUCHCHHRE BANK, LTD.",
        "phone": "",
        "website": "",
        "country_code": "NP",
        "country_code_alpha3": "NPL",
        "country_name": "NEPAL"
    },
    {
        "bin": "489325",
        "brand": "VISA",
        "type": "DEBIT",
        "category": "PLATINUM",
        "issuer": "NIC ASIA BANK, LTD.",
        "phone": "",
        "website": "",
        "country_code": "NP",
        "country_code_alpha3": "NPL",
        "country_name": "NEPAL"
    },
    {
        "bin": "489506",
        "brand": "VISA",
        "type": "CREDIT",
        "category": "CLASSIC",
        "issuer": "CITIZENS BANK INTERNATIONAL, LTD.",
        "phone": "",
        "website": "",
        "country_code": "NP",
        "country_code_alpha3": "NPL",
        "country_name": "NEPAL"
    },
    {
        "bin": "489507",
        "brand": "VISA",
        "type": "CREDIT",
        "category": "CLASSIC",
        "issuer": "CITIZENS BANK INTERNATIONAL, LTD.",
        "phone": "",
        "website": "",
        "country_code": "NP",
        "country_code_alpha3": "NPL",
        "country_name": "NEPAL"
    },
    {
        "bin": "489508",
        "brand": "VISA",
        "type": "CREDIT",
        "category": "CLASSIC",
        "issuer": "",
        "phone": "",
        "website": "",
        "country_code": "NP",
        "country_code_alpha3": "NPL",
        "country_name": "NEPAL"
    },
    {
        "bin": "489509",
        "brand": "VISA",
        "type": "DEBIT",
        "category": "CLASSIC",
        "issuer": "",
        "phone": "",
        "website": "",
        "country_code": "NP",
        "country_code_alpha3": "NPL",
        "country_name": "NEPAL"
    },
    {
        "bin": "489743",
        "brand": "VISA",
        "type": "DEBIT",
        "category": "ELECTRON",
        "issuer": "NEPAL SBI BANK, LTD.",
        "phone": "",
        "website": "",
        "country_code": "NP",
        "country_code_alpha3": "NPL",
        "country_name": "NEPAL"
    },
    {
        "bin": "490291",
        "brand": "VISA",
        "type": "DEBIT",
        "category": "CLASSIC",
        "issuer": "NEPAL INVESTMENT MEGA BANK, LTD.",
        "phone": "",
        "website": "",
        "country_code": "NP",
        "country_code_alpha3": "NPL",
        "country_name": "NEPAL"
    },
    {
        "bin": "492211",
        "brand": "VISA",
        "type": "CREDIT",
        "category": "CLASSIC",
        "issuer": "STANDARD CHARTERED BANK",
        "phone": "+97771524029",
        "website": "https://www.sc.com",
        "country_code": "NP",
        "country_code_alpha3": "NPL",
        "country_name": "NEPAL"
    },
    {
        "bin": "492469",
        "brand": "VISA",
        "type": "CREDIT",
        "category": "",
        "issuer": "KUMARI BANK, LTD.",
        "phone": "",
        "website": "http://www.kumaribank.com",
        "country_code": "NP",
        "country_code_alpha3": "NPL",
        "country_name": "NEPAL"
    },
    {
        "bin": "496646",
        "brand": "VISA",
        "type": "DEBIT",
        "category": "CLASSIC",
        "issuer": "KUMARI BANK, LTD.",
        "phone": "",
        "website": "http://www.kumaribank.com",
        "country_code": "NP",
        "country_code_alpha3": "NPL",
        "country_name": "NEPAL"
    },
    {
        "bin": "496653",
        "brand": "VISA",
        "type": "DEBIT",
        "category": "GOLD",
        "issuer": "",
        "phone": "",
        "website": "",
        "country_code": "NP",
        "country_code_alpha3": "NPL",
        "country_name": "NEPAL"
    },
    {
        "bin": "498704",
        "brand": "VISA",
        "type": "DEBIT",
        "category": "PREPAID CLASSIC",
        "issuer": "NEPAL INVESTMENT MEGA BANK, LTD.",
        "phone": "",
        "website": "",
        "country_code": "NP",
        "country_code_alpha3": "NPL",
        "country_name": "NEPAL"
    },
    {
        "bin": "498758",
        "brand": "VISA",
        "type": "DEBIT",
        "category": "PREPAID",
        "issuer": "NEPAL INVESTMENT BANK, LTD.",
        "phone": "",
        "website": "http://www.nibl.com.np",
        "country_code": "NP",
        "country_code_alpha3": "NPL",
        "country_name": "NEPAL"
    },
    {
        "bin": "503574",
        "brand": "MAESTRO",
        "type": "DEBIT",
        "category": "STANDARD",
        "issuer": "",
        "phone": "",
        "website": "",
        "country_code": "NP",
        "country_code_alpha3": "NPL",
        "country_name": "NEPAL"
    },
    {
        "bin": "518166",
        "brand": "MASTERCARD",
        "type": "CREDIT",
        "category": "STANDARD",
        "issuer": "STANDARD CHARTERED BANK NEPAL LTD.",
        "phone": "",
        "website": "",
        "country_code": "NP",
        "country_code_alpha3": "NPL",
        "country_name": "NEPAL"
    },
    {
        "bin": "521066",
        "brand": "MASTERCARD",
        "type": "DEBIT",
        "category": "STANDARD",
        "issuer": "NEPAL INVESTMENT MEGA BANK, LTD.",
        "phone": "",
        "website": "",
        "country_code": "NP",
        "country_code_alpha3": "NPL",
        "country_name": "NEPAL"
    },
    {
        "bin": "524682",
        "brand": "MASTERCARD",
        "type": "DEBIT",
        "category": "STANDARD",
        "issuer": "HIMALAYAN BANK, LTD.",
        "phone": "",
        "website": "http://www.himalayanbank.com",
        "country_code": "NP",
        "country_code_alpha3": "NPL",
        "country_name": "NEPAL"
    },
    {
        "bin": "524683",
        "brand": "MASTERCARD",
        "type": "DEBIT",
        "category": "STANDARD",
        "issuer": "HIMALAYAN BANK, LTD.",
        "phone": "",
        "website": "http://www.himalayanbank.com",
        "country_code": "NP",
        "country_code_alpha3": "NPL",
        "country_name": "NEPAL"
    },
    {
        "bin": "524684",
        "brand": "MASTERCARD",
        "type": "DEBIT",
        "category": "STANDARD",
        "issuer": "HIMALAYAN BANK, LTD.",
        "phone": "",
        "website": "http://www.himalayanbank.com",
        "country_code": "NP",
        "country_code_alpha3": "NPL",
        "country_name": "NEPAL"
    },
    {
        "bin": "529767",
        "brand": "MASTERCARD",
        "type": "DEBIT",
        "category": "GOLD",
        "issuer": "PRABHU BANK, LTD.",
        "phone": "",
        "website": "",
        "country_code": "NP",
        "country_code_alpha3": "NPL",
        "country_name": "NEPAL"
    },
    {
        "bin": "530424",
        "brand": "MASTERCARD",
        "type": "DEBIT",
        "category": "STANDARD",
        "issuer": "SIDDHARTHA BANK, LTD.",
        "phone": "",
        "website": "",
        "country_code": "NP",
        "country_code_alpha3": "NPL",
        "country_name": "NEPAL"
    },
    {
        "bin": "535964",
        "brand": "MASTERCARD",
        "type": "DEBIT",
        "category": "STANDARD",
        "issuer": "PRABHU BANK, LTD.",
        "phone": "",
        "website": "",
        "country_code": "NP",
        "country_code_alpha3": "NPL",
        "country_name": "NEPAL"
    },
    {
        "bin": "538749",
        "brand": "MASTERCARD",
        "type": "DEBIT",
        "category": "STANDARD",
        "issuer": "NIC ASIA BANK, LTD.",
        "phone": "",
        "website": "",
        "country_code": "NP",
        "country_code_alpha3": "NPL",
        "country_name": "NEPAL"
    },
    {
        "bin": "538815",
        "brand": "MASTERCARD",
        "type": "DEBIT",
        "category": "",
        "issuer": "NEPAL INVESTMENT MEGA BANK, LTD.",
        "phone": "",
        "website": "",
        "country_code": "NP",
        "country_code_alpha3": "NPL",
        "country_name": "NEPAL"
    },
    {
        "bin": "538957",
        "brand": "MASTERCARD",
        "type": "DEBIT",
        "category": "STANDARD",
        "issuer": "NEPAL SBI BANK, LTD.",
        "phone": "",
        "website": "",
        "country_code": "NP",
        "country_code_alpha3": "NPL",
        "country_name": "NEPAL"
    },
    {
        "bin": "539604",
        "brand": "MASTERCARD",
        "type": "DEBIT",
        "category": "STANDARD",
        "issuer": "NIC ASIA BANK, LTD.",
        "phone": "",
        "website": "",
        "country_code": "NP",
        "country_code_alpha3": "NPL",
        "country_name": "NEPAL"
    },
    {
        "bin": "539933",
        "brand": "MASTERCARD",
        "type": "DEBIT",
        "category": "STANDARD",
        "issuer": "HIMALAYAN BANK, LTD.",
        "phone": "",
        "website": "http://www.himalayanbank.com",
        "country_code": "NP",
        "country_code_alpha3": "NPL",
        "country_name": "NEPAL"
    },
    {
        "bin": "540357",
        "brand": "MASTERCARD",
        "type": "DEBIT",
        "category": "STANDARD",
        "issuer": "NEPAL INVESTMENT BANK, LTD.",
        "phone": "",
        "website": "http://www.nibl.com.np",
        "country_code": "NP",
        "country_code_alpha3": "NPL",
        "country_name": "NEPAL"
    },
    {
        "bin": "542157",
        "brand": "MASTERCARD",
        "type": "CREDIT",
        "category": "MIXED PRODUCT",
        "issuer": "NABIL BANK LTD.",
        "phone": "",
        "website": "",
        "country_code": "NP",
        "country_code_alpha3": "NPL",
        "country_name": "NEPAL"
    },
    {
        "bin": "543496",
        "brand": "MASTERCARD",
        "type": "CREDIT",
        "category": "MIXED PRODUCT",
        "issuer": "NABIL BANK LTD.",
        "phone": "",
        "website": "",
        "country_code": "NP",
        "country_code_alpha3": "NPL",
        "country_name": "NEPAL"
    },
    {
        "bin": "543630",
        "brand": "MASTERCARD",
        "type": "CREDIT",
        "category": "STANDARD",
        "issuer": "NEPAL GRINDLAYS BANK, LTD.",
        "phone": "",
        "website": "",
        "country_code": "NP",
        "country_code_alpha3": "NPL",
        "country_name": "NEPAL"
    },
    {
        "bin": "545030",
        "brand": "MASTERCARD",
        "type": "DEBIT",
        "category": "TITANIUM",
        "issuer": "PRABHU BANK, LTD.",
        "phone": "",
        "website": "",
        "country_code": "NP",
        "country_code_alpha3": "NPL",
        "country_name": "NEPAL"
    },
    {
        "bin": "548360",
        "brand": "MASTERCARD",
        "type": "CREDIT",
        "category": "",
        "issuer": "STANDARD CHARTERED BANK NEPAL, LTD.",
        "phone": "+97771524029",
        "website": "http://www.standardchartered.com",
        "country_code": "NP",
        "country_code_alpha3": "NPL",
        "country_name": "NEPAL"
    },
    {
        "bin": "548483",
        "brand": "MASTERCARD",
        "type": "CREDIT",
        "category": "GOLD",
        "issuer": "HIMALAYAN BANK, LTD.",
        "phone": "+97714227749",
        "website": "http://www.himalayanbank.com",
        "country_code": "NP",
        "country_code_alpha3": "NPL",
        "country_name": "NEPAL"
    },
    {
        "bin": "548493",
        "brand": "MASTERCARD",
        "type": "CREDIT",
        "category": "GOLD",
        "issuer": "HIMALAYAN BANK, LTD.",
        "phone": "+97714227749",
        "website": "http://www.himalayanbank.com",
        "country_code": "NP",
        "country_code_alpha3": "NPL",
        "country_name": "NEPAL"
    },
    {
        "bin": "548633",
        "brand": "MASTERCARD",
        "type": "CREDIT",
        "category": "GOLD",
        "issuer": "STANDARD CHARTERED BANK NEPAL, LTD.",
        "phone": "+97771524029",
        "website": "http://www.standardchartered.com",
        "country_code": "NP",
        "country_code_alpha3": "NPL",
        "country_name": "NEPAL"
    },
    {
        "bin": "548730",
        "brand": "MASTERCARD",
        "type": "CREDIT",
        "category": "STANDARD",
        "issuer": "HIMALAYAN BANK, LTD.",
        "phone": "+97714227749",
        "website": "http://www.himalayanbank.com",
        "country_code": "NP",
        "country_code_alpha3": "NPL",
        "country_name": "NEPAL"
    },
    {
        "bin": "554038",
        "brand": "MASTERCARD",
        "type": "DEBIT",
        "category": "PLATINUM",
        "issuer": "NEPAL INVESTMENT BANK, LTD.",
        "phone": "",
        "website": "http://www.nibl.com.np",
        "country_code": "NP",
        "country_code_alpha3": "NPL",
        "country_name": "NEPAL"
    },
    {
        "bin": "554370",
        "brand": "MASTERCARD",
        "type": "CREDIT",
        "category": "STANDARD",
        "issuer": "HIMALAYAN BANK, LTD.",
        "phone": "",
        "website": "http://www.himalayanbank.com",
        "country_code": "NP",
        "country_code_alpha3": "NPL",
        "country_name": "NEPAL"
    },
    {
        "bin": "554391",
        "brand": "MASTERCARD",
        "type": "CREDIT",
        "category": "GOLD",
        "issuer": "HIMALAYAN BANK, LTD.",
        "phone": "",
        "website": "http://www.himalayanbank.com",
        "country_code": "NP",
        "country_code_alpha3": "NPL",
        "country_name": "NEPAL"
    },
    {
        "bin": "555934",
        "brand": "MASTERCARD",
        "type": "CREDIT",
        "category": "STANDARD",
        "issuer": "NABIL BANK, LTD.",
        "phone": "(804) 222-1307",
        "website": "",
        "country_code": "NP",
        "country_code_alpha3": "NPL",
        "country_name": "NEPAL"
    },
    {
        "bin": "557578",
        "brand": "MASTERCARD",
        "type": "CREDIT",
        "category": "STANDARD",
        "issuer": "HIMALAYAN BANK, LTD.",
        "phone": "",
        "website": "http://www.himalayanbank.com",
        "country_code": "NP",
        "country_code_alpha3": "NPL",
        "country_name": "NEPAL"
    },
    {
        "bin": "623364",
        "brand": "CHINA UNION PAY",
        "type": "DEBIT",
        "category": "",
        "issuer": "INN FOR UNIONPAY CARD NETWORK",
        "phone": "",
        "website": "",
        "country_code": "NP",
        "country_code_alpha3": "NPL",
        "country_name": "NEPAL"
    },
    {
        "bin": "623459",
        "brand": "CHINA UNION PAY",
        "type": "DEBIT",
        "category": "PREPAID",
        "issuer": "SMARTCHOICE TECHNOLOGIES PVT.LTD.",
        "phone": "",
        "website": "",
        "country_code": "NP",
        "country_code_alpha3": "NPL",
        "country_name": "NEPAL"
    },
    {
        "bin": "623475",
        "brand": "CHINA UNION PAY",
        "type": "DEBIT",
        "category": "OTHER",
        "issuer": "INN FOR UNIONPAY CARD NETWORK",
        "phone": "",
        "website": "",
        "country_code": "NP",
        "country_code_alpha3": "NPL",
        "country_name": "NEPAL"
    },
    {
        "bin": "623477",
        "brand": "CHINA UNION PAY",
        "type": "DEBIT",
        "category": "PERSONAL",
        "issuer": "SMARTCHOICE TECHNOLOGIES PVT.LTD.",
        "phone": "",
        "website": "",
        "country_code": "NP",
        "country_code_alpha3": "NPL",
        "country_name": "NEPAL"
    },
    {
        "bin": "623499",
        "brand": "CHINA UNION PAY",
        "type": "DEBIT",
        "category": "PREPAID",
        "issuer": "HIMALAYAN BANK, LTD.",
        "phone": "",
        "website": "http://www.himalayanbank.com",
        "country_code": "NP",
        "country_code_alpha3": "NPL",
        "country_name": "NEPAL"
    },
    {
        "bin": "629102",
        "brand": "CHINA UNION PAY",
        "type": "DEBIT",
        "category": "",
        "issuer": "",
        "phone": "",
        "website": "",
        "country_code": "NP",
        "country_code_alpha3": "NPL",
        "country_name": "NEPAL"
    },
    {
        "bin": "629132",
        "brand": "CHINA UNION PAY",
        "type": "DEBIT",
        "category": "",
        "issuer": "INN FOR UNIONPAY CARD NETWORK",
        "phone": "",
        "website": "",
        "country_code": "NP",
        "country_code_alpha3": "NPL",
        "country_name": "NEPAL"
    },
    {
        "bin": "636523",
        "brand": "MAESTRO",
        "type": "DEBIT",
        "category": "STANDARD",
        "issuer": "NEPAL INDUSTRIAL DEVELOPMENT CORPORATION, LTD.",
        "phone": "",
        "website": "",
        "country_code": "NP",
        "country_code_alpha3": "NPL",
        "country_name": "NEPAL"
    }
]