[
  {
    "Street": "Paris 5",
    "City/Town": "Paris",
    "State/Province/Region": "Paris",
    "Zip/Postal Code": "75005",
    "Phone Number": "01 45 35 64 95",
    "Country": "France",
    "Latitude": "48.839641",
    "Longitude": "2.351025",
    "Full Name": "Adrien Coste",
    "Gender": "male",
    "Birthday": "1989-05-30",
    "Social Security Number": "038-97-7617",
    "Credit card brand": "VISA",
    "Credit card number": "4623381140261622",
    "Expire": "07/2026",
    "CVV": "970",
    "Country_Code": "FR"
  },
  {
    "Street": "35 Rue Ampere",
    "City/Town": "Vitry-sur-Seine",
    "State/Province/Region": "Val-de-Marne",
    "Zip/Postal Code": "94400",
    "Phone Number": "01 46 80 11 78",
    "Country": "France",
    "Latitude": "48.782963",
    "Longitude": "2.398678",
    "Full Name": "Augustin Delattre-Traore",
    "Gender": "male",
    "Birthday": "1977-06-24",
    "Social Security Number": "104-17-5564",
    "Credit card brand": "UNKNOWN",
    "Credit card number": "5612486911007102",
    "Expire": "07/2031",
    "CVV": "545",
    "Country_Code": "FR"
  },
  {
    "Street": "4 Place Saint-Epvre",
    "City/Town": "Nancy",
    "State/Province/Region": "Meurthe-et-Moselle",
    "Zip/Postal Code": "54000",
    "Phone Number": "03 83 35 45 02",
    "Country": "France",
    "Latitude": "48.696088",
    "Longitude": "6.179136",
    "Full Name": "Jules Le Collet",
    "Gender": "male",
    "Birthday": "1982-01-22",
    "Social Security Number": "150-36-3133",
    "Credit card brand": "VISA",
    "Credit card number": "4562447493645167",
    "Expire": "09/2031",
    "CVV": "697",
    "Country_Code": "FR"
  },
  {
    "Street": "9 Rue Lassus",
    "City/Town": "Paris",
    "State/Province/Region": "Paris",
    "Zip/Postal Code": "75019",
    "Phone Number": "01 42 08 43 22",
    "Country": "France",
    "Latitude": "48.875501",
    "Longitude": "2.38899",
    "Full Name": "Xavier David",
    "Gender": "male",
    "Birthday": "1981-04-08",
    "Social Security Number": "624-11-8287",
    "Credit card brand": "VISA",
    "Credit card number": "4022317125275242",
    "Expire": "02/2028",
    "CVV": "143",
    "Country_Code": "FR"
  },
  {
    "Street": "2 Rue des Grandes Arcades",
    "City/Town": "Strasbourg",
    "State/Province/Region": "Bas-Rhin",
    "Zip/Postal Code": "67000",
    "Phone Number": "03 88 32 71 55",
    "Country": "France",
    "Latitude": "48.584056",
    "Longitude": "7.746349",
    "Full Name": "Adélaïde Samson",
    "Gender": "female",
    "Birthday": "1985-03-18",
    "Social Security Number": "572-20-2410",
    "Credit card brand": "VISA",
    "Credit card number": "4574244530607078",
    "Expire": "10/2036",
    "CVV": "889",
    "Country_Code": "FR"
  },
  {
    "Street": "36 Rue de Turenne",
    "City/Town": "Paris",
    "State/Province/Region": "Paris",
    "Zip/Postal Code": "75003",
    "Phone Number": "01 42 71 36 70",
    "Country": "France",
    "Latitude": "48.857502",
    "Longitude": "2.364519",
    "Full Name": "Maryse Robin",
    "Gender": "female",
    "Birthday": "1999-05-03",
    "Social Security Number": "192-67-3069",
    "Credit card brand": "VISA",
    "Credit card number": "4396222318822511",
    "Expire": "11/2038",
    "CVV": "751",
    "Country_Code": "FR"
  },
  {
    "Street": "34 Rue du Docteur Leroy",
    "City/Town": "Le Mans",
    "State/Province/Region": "Sarthe",
    "Zip/Postal Code": "72000",
    "Phone Number": "02 43 87 78 85",
    "Country": "France",
    "Latitude": "48.002163",
    "Longitude": "0.19614",
    "Full Name": "Christiane Gregoire",
    "Gender": "female",
    "Birthday": "1987-11-01",
    "Social Security Number": "840-44-6563",
    "Credit card brand": "VISA",
    "Credit card number": "4739354431734269",
    "Expire": "09/2036",
    "CVV": "845",
    "Country_Code": "FR"
  },
  {
    "Street": "16 Rue Boileau",
    "City/Town": "Limoges",
    "State/Province/Region": "Haute-Vienne",
    "Zip/Postal Code": "87100",
    "Phone Number": "05 55 77 39 39",
    "Country": "France",
    "Latitude": "45.845259",
    "Longitude": "1.247762",
    "Full Name": "Émilie Perrin",
    "Gender": "female",
    "Birthday": "1970-05-17",
    "Social Security Number": "351-07-4988",
    "Credit card brand": "VISA",
    "Credit card number": "4971507838036177",
    "Expire": "01/2032",
    "CVV": "463",
    "Country_Code": "FR"
  },
  {
    "Street": "43 Boulevard Stalingrad",
    "City/Town": "Nice",
    "State/Province/Region": "Alpes-Maritimes",
    "Zip/Postal Code": "06300",
    "Phone Number": "04 93 26 07 21",
    "Country": "France",
    "Latitude": "43.695218",
    "Longitude": "7.286735",
    "Full Name": "Alex Germain",
    "Gender": "female",
    "Birthday": "1986-05-17",
    "Social Security Number": "279-62-8913",
    "Credit card brand": "VISA",
    "Credit card number": "4972244790903280",
    "Expire": "06/2031",
    "CVV": "229",
    "Country_Code": "FR"
  },
  {
    "Street": "19 Chemin des Mines",
    "City/Town": "Vienne",
    "State/Province/Region": "Isère",
    "Zip/Postal Code": "38200",
    "Phone Number": "04 74 31 74 60",
    "Country": "France",
    "Latitude": "45.542777",
    "Longitude": "4.85446",
    "Full Name": "Philippe Aubry",
    "Gender": "male",
    "Birthday": "1977-06-10",
    "Social Security Number": "703-71-4537",
    "Credit card brand": "MASTERCARD",
    "Credit card number": "5447127714146199",
    "Expire": "02/2028",
    "CVV": "233",
    "Country_Code": "FR"
  }
]