[
  {
    "Street": "Strada Campului 20",
    "City/Town": "Selimbar",
    "State/Province/Region": "Sibiu",
    "Zip/Postal Code": "550126",
    "Phone Number": "0269 560 188",
    "Country": "Romania",
    "Latitude": "45.770944",
    "Longitude": "24.180002",
    "Full Name": "Corvin Oprea",
    "Gender": "male",
    "Birthday": "1971-05-03",
    "Social Security Number": "593-19-4260",
    "Credit card brand": "UNKNOWN",
    "Credit card number": "5932285442157938",
    "Expire": "10/2036",
    "CVV": "600",
    "Country_Code": "RO"
  },
  {
    "Street": "Calea Moldovei 35",
    "City/Town": "Focsani",
    "State/Province/Region": "Vrancea",
    "Zip/Postal Code": "620157",
    "Phone Number": "0237 220 341",
    "Country": "Romania",
    "Latitude": "45.701223",
    "Longitude": "27.202449",
    "Full Name": "Sinică Lupu",
    "Gender": "male",
    "Birthday": "1986-04-29",
    "Social Security Number": "444-96-2238",
    "Credit card brand": "MASTERCARD",
    "Credit card number": "5466659481180338",
    "Expire": "10/2027",
    "CVV": "713",
    "Country_Code": "RO"
  },
  {
    "Street": "Callatis Str. Nr. 22",
    "City/Town": "Constanta",
    "State/Province/Region": "Constanța",
    "Zip/Postal Code": "900744",
    "Phone Number": "0241 508 002",
    "Country": "Romania",
    "Latitude": "44.173709",
    "Longitude": "28.655863",
    "Full Name": "Lascăr Vasile",
    "Gender": "male",
    "Birthday": "1994-08-10",
    "Social Security Number": "544-43-0132",
    "Credit card brand": "MASTERCARD",
    "Credit card number": "5466652760717813",
    "Expire": "02/2038",
    "CVV": "143",
    "Country_Code": "RO"
  },
  {
    "Street": "Piata Regele Ferdinand I",
    "City/Town": "Medias",
    "State/Province/Region": "Sibiu",
    "Zip/Postal Code": "551002",
    "Phone Number": "021 203 3033",
    "Country": "Romania",
    "Latitude": "46164600.0",
    "Longitude": "24350209.0",
    "Full Name": "Narcis Trifan",
    "Gender": "male",
    "Birthday": "1979-08-05",
    "Social Security Number": "276-66-1049",
    "Credit card brand": "MASTERCARD",
    "Credit card number": "5245990266799267",
    "Expire": "09/2033",
    "CVV": "309",
    "Country_Code": "RO"
  },
  {
    "Street": "Strada Actor Ion Brezoianu 51",
    "City/Town": "Bucuresti",
    "State/Province/Region": "Bucharest",
    "Zip/Postal Code": "010135",
    "Phone Number": "0730 175 100",
    "Country": "Romania",
    "Latitude": "44.438307",
    "Longitude": "26.092981",
    "Full Name": "dr. Rafael Coman",
    "Gender": "male",
    "Birthday": "1972-02-02",
    "Social Security Number": "425-97-6262",
    "Credit card brand": "MASTERCARD",
    "Credit card number": "5291023703367580",
    "Expire": "03/2027",
    "CVV": "360",
    "Country_Code": "RO"
  },
  {
    "Street": "Bulevardul Saturn 10",
    "City/Town": "Brasov",
    "State/Province/Region": "Brașov",
    "Zip/Postal Code": "500342",
    "Phone Number": "0268 313 123",
    "Country": "Romania",
    "Latitude": "45.647736",
    "Longitude": "25.628454",
    "Full Name": "dl. Pavel Veres",
    "Gender": "male",
    "Birthday": "1978-07-24",
    "Social Security Number": "490-24-9157",
    "Credit card brand": "MASTERCARD",
    "Credit card number": "5174881674107018",
    "Expire": "10/2030",
    "CVV": "305",
    "Country_Code": "RO"
  },
  {
    "Street": "Strada Capitan Pavel Zaganescu 1",
    "City/Town": "Moinesti",
    "State/Province/Region": "Bacău",
    "Zip/Postal Code": "605400",
    "Phone Number": "0234 361 212",
    "Country": "Romania",
    "Latitude": "46.481942",
    "Longitude": "26.495697",
    "Full Name": "Dorli Albu",
    "Gender": "female",
    "Birthday": "1990-06-20",
    "Social Security Number": "399-84-8838",
    "Credit card brand": "MASTERCARD",
    "Credit card number": "5495321192686443",
    "Expire": "05/2027",
    "CVV": "460",
    "Country_Code": "RO"
  },
  {
    "Street": "Piata Trandafirilor",
    "City/Town": "Targu Mures",
    "State/Province/Region": "Mureș",
    "Zip/Postal Code": "540034",
    "Phone Number": "0365 806 862",
    "Country": "Romania",
    "Latitude": "46.546495",
    "Longitude": "24.559872",
    "Full Name": "Ionică Neagu",
    "Gender": "male",
    "Birthday": "1972-06-26",
    "Social Security Number": "129-66-1098",
    "Credit card brand": "VISA",
    "Credit card number": "4461675704422222",
    "Expire": "03/2030",
    "CVV": "786",
    "Country_Code": "RO"
  },
  {
    "Street": "Strada Sesului",
    "City/Town": "Cluj-Napoca",
    "State/Province/Region": "Cluj",
    "Zip/Postal Code": "400384",
    "Phone Number": "0744 215 250",
    "Country": "Romania",
    "Latitude": "46.761717",
    "Longitude": "23.56119",
    "Full Name": "Vladimir Dragomir",
    "Gender": "male",
    "Birthday": "1976-06-03",
    "Social Security Number": "062-18-2696",
    "Credit card brand": "MASTERCARD",
    "Credit card number": "5599915160876913",
    "Expire": "09/2031",
    "CVV": "746",
    "Country_Code": "RO"
  },
  {
    "Street": "Strada Crisan",
    "City/Town": "Baia Mare",
    "State/Province/Region": "Maramureș",
    "Zip/Postal Code": "430321",
    "Phone Number": "0751 188 212",
    "Country": "Romania",
    "Latitude": "47.65935",
    "Longitude": "23.58162",
    "Full Name": "Ionuț Ciobanu",
    "Gender": "male",
    "Birthday": "1996-07-19",
    "Social Security Number": "761-17-9753",
    "Credit card brand": "MASTERCARD",
    "Credit card number": "5539057931603814",
    "Expire": "10/2026",
    "CVV": "459",
    "Country_Code": "RO"
  }
]